<?xml version="1.0" encoding="ISO-8859-1"?>
<!--XtraDeconstruct 3.0 by Primal-->
<Quests>
	<QuestDef InternalName="Event_X_MaxStationedUnitCount10_151">
		<DisplayName>Tower Defense I</DisplayName>
		<Description>Maximum Stationed Unit Count is now 10.</Description>
		<AllowQuestRejection>0</AllowQuestRejection>
		<ShortTextAccept>DEFENSE!</ShortTextAccept>
		<QuestClass>Minor</QuestClass>
		<Repeatable>0</Repeatable>
		<TriggerType>TurnNumber</TriggerType>
		<TriggerData>151</TriggerData>
		<TriggerChance>1000000</TriggerChance>
		<PostTriggerChance>0</PostTriggerChance>
		<DoNotDisplayStartPopup>1</DoNotDisplayStartPopup>
		<Image>Event_X_MaxStationedUnitCount_256.png</Image>
		<Treasure>
			<GameModifier>
				<ModType>Map</ModType>
				<Attribute>ChangeWorld</Attribute>
				<StrVal>MaxStationedUnitCount</StrVal>
				<StrVal2>10</StrVal2>
			</GameModifier>
		</Treasure>
		<QuestObjectiveDef>
			<ObjectiveID>0</ObjectiveID>
			<QuestEnd>1</QuestEnd>
		</QuestObjectiveDef>
	</QuestDef>
	<QuestDef InternalName="Event_X_MaxStationedUnitCount11_301">
		<DisplayName>Tower Defense II</DisplayName>
		<Description>Maximum Stationed Unit Count is now 11.</Description>
		<AllowQuestRejection>0</AllowQuestRejection>
		<ShortTextAccept>DEFENSE!</ShortTextAccept>
		<QuestClass>Minor</QuestClass>
		<Repeatable>0</Repeatable>
		<TriggerType>TurnNumber</TriggerType>
		<TriggerData>301</TriggerData>
		<TriggerChance>1000000</TriggerChance>
		<PostTriggerChance>0</PostTriggerChance>
		<DoNotDisplayStartPopup>1</DoNotDisplayStartPopup>
		<Image>Event_X_MaxStationedUnitCount_256.png</Image>
		<Treasure>
			<GameModifier>
				<ModType>Map</ModType>
				<Attribute>ChangeWorld</Attribute>
				<StrVal>MaxStationedUnitCount</StrVal>
				<StrVal2>11</StrVal2>
			</GameModifier>
		</Treasure>
		<QuestObjectiveDef>
			<ObjectiveID>0</ObjectiveID>
			<QuestEnd>1</QuestEnd>
		</QuestObjectiveDef>
	</QuestDef>
	<QuestDef InternalName="Event_X_MaxStationedUnitCount12_501">
		<DisplayName>Tower Defense III</DisplayName>
		<Description>Maximum Stationed Unit Count is now 12.</Description>
		<AllowQuestRejection>0</AllowQuestRejection>
		<ShortTextAccept>DEFENSE!</ShortTextAccept>
		<QuestClass>Minor</QuestClass>
		<Repeatable>0</Repeatable>
		<TriggerType>TurnNumber</TriggerType>
		<TriggerData>501</TriggerData>
		<TriggerChance>1000000</TriggerChance>
		<PostTriggerChance>0</PostTriggerChance>
		<DoNotDisplayStartPopup>1</DoNotDisplayStartPopup>
		<Image>Event_X_MaxStationedUnitCount_256.png</Image>
		<Treasure>
			<GameModifier>
				<ModType>Map</ModType>
				<Attribute>ChangeWorld</Attribute>
				<StrVal>MaxStationedUnitCount</StrVal>
				<StrVal2>12</StrVal2>
			</GameModifier>
		</Treasure>
		<QuestObjectiveDef>
			<ObjectiveID>0</ObjectiveID>
			<QuestEnd>1</QuestEnd>
		</QuestObjectiveDef>
	</QuestDef>
</Quests>
