<?xml version="1.0"?>
<Container>
  <QuestDef InternalName="Event_Assassinations">
    <DisplayName>Assassinations</DisplayName>
    <Description>A hidden cult of religious fanatics have performed several attacks on annual gatherings between your most ingenious researchers. None survived the attacks, and the assassins even comitted suicide after their treasonous acts. By studying their scripture you were able to determine that they believed the Cataclysm were God's Judgement on all. Therefore, to remake the world to fit your own society was the greatest sin to them. 

It will take time to replace the researchers. For the next 25 turns your research is reduced. It starts out being reduced by 50%, then that negative modifier is changed by 2% every turn (50% then 48% then 46% and so on) until it is completely gone after 25 turns.</Description>
   <IsStartingPointQuest>0</IsStartingPointQuest>
    <AllowQuestRejection>0</AllowQuestRejection>
   <ShortTextAccept>An unfortunate blow to our research efforts.</ShortTextAccept>
    <QuestClass>Minor</QuestClass>
    <Repeatable>0</Repeatable>
   <TriggerType>TurnNumber</TriggerType>
    <TriggerData>125</TriggerData>
    <TriggerChance>5</TriggerChance>
    <PostTriggerChance>5</PostTriggerChance>

    <TriggerOrigin>EventLocation</TriggerOrigin>
    <Image>K_Men_Assassin_Card_01.png</Image>

    <Treasure>
      <GameModifier>
        <ModType>Player</ModType>
        <Attribute>AbilityBonus</Attribute>
        <StrVal>A_Research</StrVal>
        <Value>-2</Value>
        <Duration>1</Duration>
      </GameModifier>
      <GameModifier>
        <ModType>Player</ModType>
        <Attribute>AbilityBonus</Attribute>
        <StrVal>A_Research</StrVal>
        <Value>-2</Value>
        <Duration>2</Duration>
      </GameModifier>
      <GameModifier>
        <ModType>Player</ModType>
        <Attribute>AbilityBonus</Attribute>
        <StrVal>A_Research</StrVal>
        <Value>-2</Value>
        <Duration>3</Duration>
      </GameModifier>
      <GameModifier>
        <ModType>Player</ModType>
        <Attribute>AbilityBonus</Attribute>
        <StrVal>A_Research</StrVal>
        <Value>-2</Value>
        <Duration>4</Duration>
      </GameModifier>
      <GameModifier>
        <ModType>Player</ModType>
        <Attribute>AbilityBonus</Attribute>
        <StrVal>A_Research</StrVal>
        <Value>-2</Value>
        <Duration>5</Duration>
      </GameModifier>
      <GameModifier>
        <ModType>Player</ModType>
        <Attribute>AbilityBonus</Attribute>
        <StrVal>A_Research</StrVal>
        <Value>-2</Value>
        <Duration>6</Duration>
      </GameModifier>
      <GameModifier>
        <ModType>Player</ModType>
        <Attribute>AbilityBonus</Attribute>
        <StrVal>A_Research</StrVal>
        <Value>-2</Value>
        <Duration>7</Duration>
      </GameModifier>
      <GameModifier>
        <ModType>Player</ModType>
        <Attribute>AbilityBonus</Attribute>
        <StrVal>A_Research</StrVal>
        <Value>-2</Value>
        <Duration>8</Duration>
      </GameModifier>
      <GameModifier>
        <ModType>Player</ModType>
        <Attribute>AbilityBonus</Attribute>
        <StrVal>A_Research</StrVal>
        <Value>-2</Value>
        <Duration>9</Duration>
      </GameModifier>
      <GameModifier>
        <ModType>Player</ModType>
        <Attribute>AbilityBonus</Attribute>
        <StrVal>A_Research</StrVal>
        <Value>-2</Value>
        <Duration>10</Duration>
      </GameModifier>
      <GameModifier>
        <ModType>Player</ModType>
        <Attribute>AbilityBonus</Attribute>
        <StrVal>A_Research</StrVal>
        <Value>-2</Value>
        <Duration>11</Duration>
      </GameModifier>
      <GameModifier>
        <ModType>Player</ModType>
        <Attribute>AbilityBonus</Attribute>
        <StrVal>A_Research</StrVal>
        <Value>-2</Value>
        <Duration>12</Duration>
      </GameModifier>
      <GameModifier>
        <ModType>Player</ModType>
        <Attribute>AbilityBonus</Attribute>
        <StrVal>A_Research</StrVal>
        <Value>-2</Value>
        <Duration>13</Duration>
      </GameModifier>
      <GameModifier>
        <ModType>Player</ModType>
        <Attribute>AbilityBonus</Attribute>
        <StrVal>A_Research</StrVal>
        <Value>-2</Value>
        <Duration>14</Duration>
      </GameModifier>
      <GameModifier>
        <ModType>Player</ModType>
        <Attribute>AbilityBonus</Attribute>
        <StrVal>A_Research</StrVal>
        <Value>-2</Value>
        <Duration>15</Duration>
      </GameModifier>
      <GameModifier>
        <ModType>Player</ModType>
        <Attribute>AbilityBonus</Attribute>
        <StrVal>A_Research</StrVal>
        <Value>-2</Value>
        <Duration>16</Duration>
      </GameModifier>
      <GameModifier>
        <ModType>Player</ModType>
        <Attribute>AbilityBonus</Attribute>
        <StrVal>A_Research</StrVal>
        <Value>-2</Value>
        <Duration>17</Duration>
      </GameModifier>
      <GameModifier>
        <ModType>Player</ModType>
        <Attribute>AbilityBonus</Attribute>
        <StrVal>A_Research</StrVal>
        <Value>-2</Value>
        <Duration>18</Duration>
      </GameModifier>
      <GameModifier>
        <ModType>Player</ModType>
        <Attribute>AbilityBonus</Attribute>
        <StrVal>A_Research</StrVal>
        <Value>-2</Value>
        <Duration>19</Duration>
      </GameModifier>
      <GameModifier>
        <ModType>Player</ModType>
        <Attribute>AbilityBonus</Attribute>
        <StrVal>A_Research</StrVal>
        <Value>-2</Value>
        <Duration>20</Duration>
      </GameModifier>
      <GameModifier>
        <ModType>Player</ModType>
        <Attribute>AbilityBonus</Attribute>
        <StrVal>A_Research</StrVal>
        <Value>-2</Value>
        <Duration>21</Duration>
      </GameModifier>
      <GameModifier>
        <ModType>Player</ModType>
        <Attribute>AbilityBonus</Attribute>
        <StrVal>A_Research</StrVal>
        <Value>-2</Value>
        <Duration>22</Duration>
      </GameModifier>
      <GameModifier>
        <ModType>Player</ModType>
        <Attribute>AbilityBonus</Attribute>
        <StrVal>A_Research</StrVal>
        <Value>-2</Value>
        <Duration>23</Duration>
      </GameModifier>
      <GameModifier>
        <ModType>Player</ModType>
        <Attribute>AbilityBonus</Attribute>
        <StrVal>A_Research</StrVal>
        <Value>-2</Value>
        <Duration>24</Duration>
      </GameModifier>
      <GameModifier>
        <ModType>Player</ModType>
        <Attribute>AbilityBonus</Attribute>
        <StrVal>A_Research</StrVal>
        <Value>-2</Value>
        <Duration>25</Duration>
      </GameModifier>
    </Treasure>
    <QuestObjectiveDef>
      <ObjectiveID>0</ObjectiveID>
      <QuestEnd>1</QuestEnd>
    </QuestObjectiveDef>
  </QuestDef>
</Container>
