<?xml version="1.0" encoding="ISO-8859-1"?>
<!--Necromancy Revamped by Dhuran-->
<!--XtraDeconstruct 3.0 by Primal-->
<UnitTypes>
	<UnitType InternalName="NS_Simple_Zombie">
		<DisplayName>Zombie #U</DisplayName>
		<Description>Remains of those recently killed, called back to service by necromancers.</Description>
		<CreatureType>Undead</CreatureType>
		<CanBeDesigned>0</CanBeDesigned>
		<IsSovereign>0</IsSovereign>
		<AllowGrouping>0</AllowGrouping>
		<HasWages>0</HasWages>
		<LevelMilestone InternalName="L1">
			<Level>1</Level>
			<UnitStat_Accuracy>75</UnitStat_Accuracy>
			<UnitStat_Attack_Pierce>0</UnitStat_Attack_Pierce>
			<UnitStat_ChanceToCrit>1</UnitStat_ChanceToCrit>
			<UnitStat_CombatSpeed>16</UnitStat_CombatSpeed>
			<UnitStat_HitPoints>8</UnitStat_HitPoints>
			<UnitStat_Intelligence>1</UnitStat_Intelligence>
			<UnitStat_Moves>3</UnitStat_Moves>
			<UnitStat_BG_IsHumanoid>1</UnitStat_BG_IsHumanoid>
			<UnitStat_BG_IsRace_Undead>1</UnitStat_BG_IsRace_Undead>
			<UnitStat_BG_IsEmpire>1</UnitStat_BG_IsEmpire>
			<UnitStat_BG_IsImmortal>1</UnitStat_BG_IsImmortal>
			<UnitStat_BG_IsUndead>1</UnitStat_BG_IsUndead>
			<UnitStat_ImmuneToFear>1</UnitStat_ImmuneToFear>
			<UnitStat_BG_IsNotAlive>1</UnitStat_BG_IsNotAlive>
		</LevelMilestone>
		<LevelMilestone InternalName="L2">
			<Level>2</Level>
			<UnitStat_Accuracy>75</UnitStat_Accuracy>
			<UnitStat_Attack_Pierce>0</UnitStat_Attack_Pierce>
			<UnitStat_ChanceToCrit>1</UnitStat_ChanceToCrit>
			<UnitStat_CombatSpeed>16</UnitStat_CombatSpeed>
			<UnitStat_HitPoints>8</UnitStat_HitPoints>
			<UnitStat_Intelligence>1</UnitStat_Intelligence>
			<UnitStat_Moves>3</UnitStat_Moves>
		</LevelMilestone>
		<LevelMilestone InternalName="L3">
			<Level>3</Level>
			<UnitStat_Accuracy>75</UnitStat_Accuracy>
			<UnitStat_Attack_Pierce>0</UnitStat_Attack_Pierce>
			<UnitStat_ChanceToCrit>1</UnitStat_ChanceToCrit>
			<UnitStat_CombatSpeed>16</UnitStat_CombatSpeed>
			<UnitStat_HitPoints>8</UnitStat_HitPoints>
			<UnitStat_Intelligence>1</UnitStat_Intelligence>
			<UnitStat_Moves>3</UnitStat_Moves>
		</LevelMilestone>
		<LevelMilestone InternalName="L4">
			<Level>4</Level>
			<UnitStat_Accuracy>75</UnitStat_Accuracy>
			<UnitStat_Attack_Pierce>0</UnitStat_Attack_Pierce>
			<UnitStat_ChanceToCrit>1</UnitStat_ChanceToCrit>
			<UnitStat_CombatSpeed>16</UnitStat_CombatSpeed>
			<UnitStat_HitPoints>8</UnitStat_HitPoints>
			<UnitStat_Intelligence>1</UnitStat_Intelligence>
			<UnitStat_Moves>3</UnitStat_Moves>
		</LevelMilestone>
		<LevelMilestone InternalName="L5">
			<Level>5</Level>
			<UnitStat_Accuracy>75</UnitStat_Accuracy>
			<UnitStat_Attack_Pierce>0</UnitStat_Attack_Pierce>
			<UnitStat_ChanceToCrit>1</UnitStat_ChanceToCrit>
			<UnitStat_CombatSpeed>16</UnitStat_CombatSpeed>
			<UnitStat_HitPoints>8</UnitStat_HitPoints>
			<UnitStat_Intelligence>1</UnitStat_Intelligence>
			<UnitStat_Moves>3</UnitStat_Moves>
		</LevelMilestone>
		<LevelMilestone InternalName="L6">
			<Level>6</Level>
			<UnitStat_Accuracy>75</UnitStat_Accuracy>
			<UnitStat_Attack_Pierce>0</UnitStat_Attack_Pierce>
			<UnitStat_ChanceToCrit>1</UnitStat_ChanceToCrit>
			<UnitStat_CombatSpeed>16</UnitStat_CombatSpeed>
			<UnitStat_HitPoints>8</UnitStat_HitPoints>
			<UnitStat_Intelligence>1</UnitStat_Intelligence>
			<UnitStat_Moves>3</UnitStat_Moves>
		</LevelMilestone>
		<LevelMilestone InternalName="L7">
			<Level>7</Level>
			<UnitStat_Accuracy>75</UnitStat_Accuracy>
			<UnitStat_Attack_Pierce>0</UnitStat_Attack_Pierce>
			<UnitStat_ChanceToCrit>1</UnitStat_ChanceToCrit>
			<UnitStat_CombatSpeed>16</UnitStat_CombatSpeed>
			<UnitStat_HitPoints>8</UnitStat_HitPoints>
			<UnitStat_Intelligence>1</UnitStat_Intelligence>
			<UnitStat_Moves>3</UnitStat_Moves>
		</LevelMilestone>
		<LevelMilestone InternalName="L8">
			<Level>8</Level>
			<UnitStat_Accuracy>75</UnitStat_Accuracy>
			<UnitStat_Attack_Pierce>0</UnitStat_Attack_Pierce>
			<UnitStat_ChanceToCrit>1</UnitStat_ChanceToCrit>
			<UnitStat_CombatSpeed>16</UnitStat_CombatSpeed>
			<UnitStat_HitPoints>8</UnitStat_HitPoints>
			<UnitStat_Intelligence>1</UnitStat_Intelligence>
			<UnitStat_Moves>3</UnitStat_Moves>
		</LevelMilestone>
		<LevelMilestone InternalName="L9">
			<Level>9</Level>
			<UnitStat_Accuracy>75</UnitStat_Accuracy>
			<UnitStat_Attack_Pierce>0</UnitStat_Attack_Pierce>
			<UnitStat_ChanceToCrit>1</UnitStat_ChanceToCrit>
			<UnitStat_CombatSpeed>16</UnitStat_CombatSpeed>
			<UnitStat_HitPoints>8</UnitStat_HitPoints>
			<UnitStat_Intelligence>1</UnitStat_Intelligence>
			<UnitStat_Moves>3</UnitStat_Moves>
		</LevelMilestone>
		<LevelMilestone InternalName="L10">
			<Level>10</Level>
			<UnitStat_Accuracy>75</UnitStat_Accuracy>
			<UnitStat_Attack_Pierce>0</UnitStat_Attack_Pierce>
			<UnitStat_ChanceToCrit>1</UnitStat_ChanceToCrit>
			<UnitStat_CombatSpeed>16</UnitStat_CombatSpeed>
			<UnitStat_HitPoints>8</UnitStat_HitPoints>
			<UnitStat_Intelligence>1</UnitStat_Intelligence>
			<UnitStat_Moves>3</UnitStat_Moves>
		</LevelMilestone>
		<LevelMilestone InternalName="L11">
			<Level>11</Level>
			<UnitStat_Accuracy>75</UnitStat_Accuracy>
			<UnitStat_Attack_Pierce>0</UnitStat_Attack_Pierce>
			<UnitStat_ChanceToCrit>1</UnitStat_ChanceToCrit>
			<UnitStat_CombatSpeed>16</UnitStat_CombatSpeed>
			<UnitStat_HitPoints>8</UnitStat_HitPoints>
			<UnitStat_Intelligence>1</UnitStat_Intelligence>
			<UnitStat_Moves>3</UnitStat_Moves>
		</LevelMilestone>
		<LevelMilestone InternalName="L12">
			<Level>12</Level>
			<UnitStat_Accuracy>75</UnitStat_Accuracy>
			<UnitStat_Attack_Pierce>0</UnitStat_Attack_Pierce>
			<UnitStat_ChanceToCrit>1</UnitStat_ChanceToCrit>
			<UnitStat_CombatSpeed>16</UnitStat_CombatSpeed>
			<UnitStat_HitPoints>8</UnitStat_HitPoints>
			<UnitStat_Intelligence>1</UnitStat_Intelligence>
			<UnitStat_Moves>3</UnitStat_Moves>
		</LevelMilestone>
		<LevelMilestone InternalName="L13">
			<Level>13</Level>
			<UnitStat_Accuracy>75</UnitStat_Accuracy>
			<UnitStat_Attack_Pierce>0</UnitStat_Attack_Pierce>
			<UnitStat_ChanceToCrit>1</UnitStat_ChanceToCrit>
			<UnitStat_CombatSpeed>16</UnitStat_CombatSpeed>
			<UnitStat_HitPoints>8</UnitStat_HitPoints>
			<UnitStat_Intelligence>1</UnitStat_Intelligence>
			<UnitStat_Moves>3</UnitStat_Moves>
		</LevelMilestone>
		<LevelMilestone InternalName="L14">
			<Level>14</Level>
			<UnitStat_Accuracy>75</UnitStat_Accuracy>
			<UnitStat_Attack_Pierce>0</UnitStat_Attack_Pierce>
			<UnitStat_ChanceToCrit>1</UnitStat_ChanceToCrit>
			<UnitStat_CombatSpeed>16</UnitStat_CombatSpeed>
			<UnitStat_HitPoints>8</UnitStat_HitPoints>
			<UnitStat_Intelligence>1</UnitStat_Intelligence>
			<UnitStat_Moves>3</UnitStat_Moves>
		</LevelMilestone>
		<LevelMilestone InternalName="L15">
			<Level>15</Level>
			<UnitStat_Accuracy>75</UnitStat_Accuracy>
			<UnitStat_Attack_Pierce>0</UnitStat_Attack_Pierce>
			<UnitStat_ChanceToCrit>1</UnitStat_ChanceToCrit>
			<UnitStat_CombatSpeed>16</UnitStat_CombatSpeed>
			<UnitStat_HitPoints>8</UnitStat_HitPoints>
			<UnitStat_Intelligence>1</UnitStat_Intelligence>
			<UnitStat_Moves>3</UnitStat_Moves>
		</LevelMilestone>
		<LevelMilestone InternalName="L16">
			<Level>16</Level>
			<UnitStat_Accuracy>75</UnitStat_Accuracy>
			<UnitStat_Attack_Pierce>0</UnitStat_Attack_Pierce>
			<UnitStat_ChanceToCrit>1</UnitStat_ChanceToCrit>
			<UnitStat_CombatSpeed>16</UnitStat_CombatSpeed>
			<UnitStat_HitPoints>8</UnitStat_HitPoints>
			<UnitStat_Intelligence>1</UnitStat_Intelligence>
			<UnitStat_Moves>3</UnitStat_Moves>
		</LevelMilestone>
		<LevelMilestone InternalName="L17">
			<Level>17</Level>
			<UnitStat_Accuracy>75</UnitStat_Accuracy>
			<UnitStat_Attack_Pierce>0</UnitStat_Attack_Pierce>
			<UnitStat_ChanceToCrit>1</UnitStat_ChanceToCrit>
			<UnitStat_CombatSpeed>16</UnitStat_CombatSpeed>
			<UnitStat_HitPoints>8</UnitStat_HitPoints>
			<UnitStat_Intelligence>1</UnitStat_Intelligence>
			<UnitStat_Moves>3</UnitStat_Moves>
		</LevelMilestone>
		<LevelMilestone InternalName="L18">
			<Level>18</Level>
			<UnitStat_Accuracy>75</UnitStat_Accuracy>
			<UnitStat_Attack_Pierce>0</UnitStat_Attack_Pierce>
			<UnitStat_ChanceToCrit>1</UnitStat_ChanceToCrit>
			<UnitStat_CombatSpeed>16</UnitStat_CombatSpeed>
			<UnitStat_HitPoints>8</UnitStat_HitPoints>
			<UnitStat_Intelligence>1</UnitStat_Intelligence>
			<UnitStat_Moves>3</UnitStat_Moves>
		</LevelMilestone>
		<LevelMilestone InternalName="L19">
			<Level>19</Level>
			<UnitStat_Accuracy>75</UnitStat_Accuracy>
			<UnitStat_Attack_Pierce>0</UnitStat_Attack_Pierce>
			<UnitStat_ChanceToCrit>1</UnitStat_ChanceToCrit>
			<UnitStat_CombatSpeed>16</UnitStat_CombatSpeed>
			<UnitStat_HitPoints>8</UnitStat_HitPoints>
			<UnitStat_Intelligence>1</UnitStat_Intelligence>
			<UnitStat_Moves>3</UnitStat_Moves>
		</LevelMilestone>
		<LevelMilestone InternalName="L20">
			<Level>20</Level>
			<UnitStat_Accuracy>75</UnitStat_Accuracy>
			<UnitStat_Attack_Pierce>0</UnitStat_Attack_Pierce>
			<UnitStat_ChanceToCrit>1</UnitStat_ChanceToCrit>
			<UnitStat_CombatSpeed>16</UnitStat_CombatSpeed>
			<UnitStat_HitPoints>8</UnitStat_HitPoints>
			<UnitStat_Intelligence>1</UnitStat_Intelligence>
			<UnitStat_Moves>3</UnitStat_Moves>
		</LevelMilestone>
		<SelectedAbilityBonusOption>ImmuneToPoison</SelectedAbilityBonusOption>
		<SelectedAbilityBonusOption>ImmuneToCriticals</SelectedAbilityBonusOption>
		<SelectedAbilityBonusOption>Inaccurate</SelectedAbilityBonusOption>
		<Backstory></Backstory>
		<Equipment>Club</Equipment>
		<Equipment>ChainBreastpiece_Skeleton</Equipment>
		<Equipment>K_Male_Head_02</Equipment>
		<AnimationPack>SkeletonAnimationPack</AnimationPack>
		<AnimationParticleEffect>Awaken,_Skeleton_Awaken,0.0,10.0,0.0,1.5</AnimationParticleEffect>
		<BattleAnimationBehavior>Melee</BattleAnimationBehavior>
		<ClothMapScale>1.6</ClothMapScale>
		<Color_Clothing1>185,173,168,255</Color_Clothing1>
		<Color_Clothing2>185,173,168,255</Color_Clothing2>
		<Color_Hair>50,50,50,255</Color_Hair>
		<Color_Metal>150,155,135,255</Color_Metal>
		<Color_Skin>206,195,181,255</Color_Skin>
		<CutSceneDataPack>DefaultUnitCutscenePack</CutSceneDataPack>
		<EyeTexture>Eyeblink_M_Dead.png</EyeTexture>
		<InfoCardBackground>BG_BarrenForest</InfoCardBackground>
		<ModelPath>K_Male_Mesh_01.hkb</ModelPath>
		<ModelScale>1</ModelScale>
		<OnHitParticleName>Bloody_OnHit</OnHitParticleName>
		<SkeletonPath>K_Male_Skeleton_01.hkb</SkeletonPath>
		<SoundPack>SoundPack_Butcherman</SoundPack>
		<TacticalModelScale>1.5</TacticalModelScale>
		<Texture_Eyes>Eyeblink_M_Dead.png</Texture_Eyes>
		<Texture_Skin>K_Male_ButchermanSkin_Texture_01.dds</Texture_Skin>
		<UnitModelType>WraithMale</UnitModelType>
		<AlwaysInTileCenter>1</AlwaysInTileCenter>
		<SelectedAbilityBonusOption>Ability_X_BloodCreatures</SelectedAbilityBonusOption>
	</UnitType>
	<UnitType InternalName="RR_Skeleton">
		<DisplayName>Skeletons #U</DisplayName>
		<Description>Remains of those long dead, called back to service by necromancers.</Description>
		<CanBeDesigned>1</CanBeDesigned>
		<CreatureType>Undead</CreatureType>
		<AdditionalTrainingTurns>10</AdditionalTrainingTurns>
		<HasWages>0</HasWages>
		<AllowGrouping>1</AllowGrouping>
		<IsSovereign>0</IsSovereign>
		<ProductionRequirement>
			<Type>Resource</Type>
			<Attribute>Mana</Attribute>
			<Value>6.67</Value>
		</ProductionRequirement>
		<LevelMilestone InternalName="L1">
			<Level>1</Level>
			<UnitStat_Accuracy>75</UnitStat_Accuracy>
			<UnitStat_Attack_Pierce>0</UnitStat_Attack_Pierce>
			<UnitStat_ChanceToCrit>1</UnitStat_ChanceToCrit>
			<UnitStat_CombatSpeed>18</UnitStat_CombatSpeed>
			<UnitStat_HitPoints>6</UnitStat_HitPoints>
			<UnitStat_Intelligence>1</UnitStat_Intelligence>
			<UnitStat_Moves>3</UnitStat_Moves>
			<UnitStat_BG_IsHumanoid>1</UnitStat_BG_IsHumanoid>
			<UnitStat_BG_IsRace_Undead>1</UnitStat_BG_IsRace_Undead>
			<UnitStat_BG_IsEmpire>1</UnitStat_BG_IsEmpire>
			<UnitStat_BG_IsImmortal>1</UnitStat_BG_IsImmortal>
			<UnitStat_BG_IsUndead>1</UnitStat_BG_IsUndead>
			<UnitStat_ImmuneToFear>1</UnitStat_ImmuneToFear>
			<UnitStat_BG_IsNotAlive>1</UnitStat_BG_IsNotAlive>
		</LevelMilestone>
		<LevelMilestone InternalName="L2">
			<Level>2</Level>
			<UnitStat_Accuracy>75</UnitStat_Accuracy>
			<UnitStat_Attack_Pierce>0</UnitStat_Attack_Pierce>
			<UnitStat_ChanceToCrit>1</UnitStat_ChanceToCrit>
			<UnitStat_CombatSpeed>18</UnitStat_CombatSpeed>
			<UnitStat_HitPoints>6</UnitStat_HitPoints>
			<UnitStat_Intelligence>1</UnitStat_Intelligence>
			<UnitStat_Moves>3</UnitStat_Moves>
		</LevelMilestone>
		<LevelMilestone InternalName="L3">
			<Level>3</Level>
			<UnitStat_Accuracy>75</UnitStat_Accuracy>
			<UnitStat_Attack_Pierce>0</UnitStat_Attack_Pierce>
			<UnitStat_ChanceToCrit>1</UnitStat_ChanceToCrit>
			<UnitStat_CombatSpeed>18</UnitStat_CombatSpeed>
			<UnitStat_HitPoints>6</UnitStat_HitPoints>
			<UnitStat_Intelligence>1</UnitStat_Intelligence>
			<UnitStat_Moves>3</UnitStat_Moves>
		</LevelMilestone>
		<LevelMilestone InternalName="L4">
			<Level>4</Level>
			<UnitStat_Accuracy>75</UnitStat_Accuracy>
			<UnitStat_Attack_Pierce>0</UnitStat_Attack_Pierce>
			<UnitStat_ChanceToCrit>1</UnitStat_ChanceToCrit>
			<UnitStat_CombatSpeed>18</UnitStat_CombatSpeed>
			<UnitStat_HitPoints>6</UnitStat_HitPoints>
			<UnitStat_Intelligence>1</UnitStat_Intelligence>
			<UnitStat_Moves>3</UnitStat_Moves>
		</LevelMilestone>
		<LevelMilestone InternalName="L5">
			<Level>5</Level>
			<UnitStat_Accuracy>75</UnitStat_Accuracy>
			<UnitStat_Attack_Pierce>0</UnitStat_Attack_Pierce>
			<UnitStat_ChanceToCrit>1</UnitStat_ChanceToCrit>
			<UnitStat_CombatSpeed>18</UnitStat_CombatSpeed>
			<UnitStat_HitPoints>6</UnitStat_HitPoints>
			<UnitStat_Intelligence>1</UnitStat_Intelligence>
			<UnitStat_Moves>3</UnitStat_Moves>
		</LevelMilestone>
		<LevelMilestone InternalName="L6">
			<Level>6</Level>
			<UnitStat_Accuracy>75</UnitStat_Accuracy>
			<UnitStat_Attack_Pierce>0</UnitStat_Attack_Pierce>
			<UnitStat_ChanceToCrit>1</UnitStat_ChanceToCrit>
			<UnitStat_CombatSpeed>18</UnitStat_CombatSpeed>
			<UnitStat_HitPoints>6</UnitStat_HitPoints>
			<UnitStat_Intelligence>1</UnitStat_Intelligence>
			<UnitStat_Moves>3</UnitStat_Moves>
		</LevelMilestone>
		<LevelMilestone InternalName="L7">
			<Level>7</Level>
			<UnitStat_Accuracy>75</UnitStat_Accuracy>
			<UnitStat_Attack_Pierce>0</UnitStat_Attack_Pierce>
			<UnitStat_ChanceToCrit>1</UnitStat_ChanceToCrit>
			<UnitStat_CombatSpeed>18</UnitStat_CombatSpeed>
			<UnitStat_HitPoints>6</UnitStat_HitPoints>
			<UnitStat_Intelligence>1</UnitStat_Intelligence>
			<UnitStat_Moves>3</UnitStat_Moves>
		</LevelMilestone>
		<LevelMilestone InternalName="L8">
			<Level>8</Level>
			<UnitStat_Accuracy>75</UnitStat_Accuracy>
			<UnitStat_Attack_Pierce>0</UnitStat_Attack_Pierce>
			<UnitStat_ChanceToCrit>1</UnitStat_ChanceToCrit>
			<UnitStat_CombatSpeed>18</UnitStat_CombatSpeed>
			<UnitStat_HitPoints>6</UnitStat_HitPoints>
			<UnitStat_Intelligence>1</UnitStat_Intelligence>
			<UnitStat_Moves>3</UnitStat_Moves>
		</LevelMilestone>
		<LevelMilestone InternalName="L9">
			<Level>9</Level>
			<UnitStat_Accuracy>75</UnitStat_Accuracy>
			<UnitStat_Attack_Pierce>0</UnitStat_Attack_Pierce>
			<UnitStat_ChanceToCrit>1</UnitStat_ChanceToCrit>
			<UnitStat_CombatSpeed>18</UnitStat_CombatSpeed>
			<UnitStat_HitPoints>6</UnitStat_HitPoints>
			<UnitStat_Intelligence>1</UnitStat_Intelligence>
			<UnitStat_Moves>3</UnitStat_Moves>
		</LevelMilestone>
		<LevelMilestone InternalName="L10">
			<Level>10</Level>
			<UnitStat_Accuracy>75</UnitStat_Accuracy>
			<UnitStat_Attack_Pierce>0</UnitStat_Attack_Pierce>
			<UnitStat_ChanceToCrit>1</UnitStat_ChanceToCrit>
			<UnitStat_CombatSpeed>18</UnitStat_CombatSpeed>
			<UnitStat_HitPoints>6</UnitStat_HitPoints>
			<UnitStat_Intelligence>1</UnitStat_Intelligence>
			<UnitStat_Moves>3</UnitStat_Moves>
		</LevelMilestone>
		<LevelMilestone InternalName="L11">
			<Level>11</Level>
			<UnitStat_Accuracy>75</UnitStat_Accuracy>
			<UnitStat_Attack_Pierce>0</UnitStat_Attack_Pierce>
			<UnitStat_ChanceToCrit>1</UnitStat_ChanceToCrit>
			<UnitStat_CombatSpeed>18</UnitStat_CombatSpeed>
			<UnitStat_HitPoints>6</UnitStat_HitPoints>
			<UnitStat_Intelligence>1</UnitStat_Intelligence>
			<UnitStat_Moves>3</UnitStat_Moves>
		</LevelMilestone>
		<LevelMilestone InternalName="L12">
			<Level>12</Level>
			<UnitStat_Accuracy>75</UnitStat_Accuracy>
			<UnitStat_Attack_Pierce>0</UnitStat_Attack_Pierce>
			<UnitStat_ChanceToCrit>1</UnitStat_ChanceToCrit>
			<UnitStat_CombatSpeed>18</UnitStat_CombatSpeed>
			<UnitStat_HitPoints>6</UnitStat_HitPoints>
			<UnitStat_Intelligence>1</UnitStat_Intelligence>
			<UnitStat_Moves>3</UnitStat_Moves>
		</LevelMilestone>
		<LevelMilestone InternalName="L13">
			<Level>13</Level>
			<UnitStat_Accuracy>75</UnitStat_Accuracy>
			<UnitStat_Attack_Pierce>0</UnitStat_Attack_Pierce>
			<UnitStat_ChanceToCrit>1</UnitStat_ChanceToCrit>
			<UnitStat_CombatSpeed>18</UnitStat_CombatSpeed>
			<UnitStat_HitPoints>6</UnitStat_HitPoints>
			<UnitStat_Intelligence>1</UnitStat_Intelligence>
			<UnitStat_Moves>3</UnitStat_Moves>
		</LevelMilestone>
		<LevelMilestone InternalName="L14">
			<Level>14</Level>
			<UnitStat_Accuracy>75</UnitStat_Accuracy>
			<UnitStat_Attack_Pierce>0</UnitStat_Attack_Pierce>
			<UnitStat_ChanceToCrit>1</UnitStat_ChanceToCrit>
			<UnitStat_CombatSpeed>18</UnitStat_CombatSpeed>
			<UnitStat_HitPoints>6</UnitStat_HitPoints>
			<UnitStat_Intelligence>1</UnitStat_Intelligence>
			<UnitStat_Moves>3</UnitStat_Moves>
		</LevelMilestone>
		<LevelMilestone InternalName="L15">
			<Level>15</Level>
			<UnitStat_Accuracy>75</UnitStat_Accuracy>
			<UnitStat_Attack_Pierce>0</UnitStat_Attack_Pierce>
			<UnitStat_ChanceToCrit>1</UnitStat_ChanceToCrit>
			<UnitStat_CombatSpeed>18</UnitStat_CombatSpeed>
			<UnitStat_HitPoints>6</UnitStat_HitPoints>
			<UnitStat_Intelligence>1</UnitStat_Intelligence>
			<UnitStat_Moves>3</UnitStat_Moves>
		</LevelMilestone>
		<LevelMilestone InternalName="L16">
			<Level>16</Level>
			<UnitStat_Accuracy>75</UnitStat_Accuracy>
			<UnitStat_Attack_Pierce>0</UnitStat_Attack_Pierce>
			<UnitStat_ChanceToCrit>1</UnitStat_ChanceToCrit>
			<UnitStat_CombatSpeed>18</UnitStat_CombatSpeed>
			<UnitStat_HitPoints>6</UnitStat_HitPoints>
			<UnitStat_Intelligence>1</UnitStat_Intelligence>
			<UnitStat_Moves>3</UnitStat_Moves>
		</LevelMilestone>
		<LevelMilestone InternalName="L17">
			<Level>17</Level>
			<UnitStat_Accuracy>75</UnitStat_Accuracy>
			<UnitStat_Attack_Pierce>0</UnitStat_Attack_Pierce>
			<UnitStat_ChanceToCrit>1</UnitStat_ChanceToCrit>
			<UnitStat_CombatSpeed>18</UnitStat_CombatSpeed>
			<UnitStat_HitPoints>6</UnitStat_HitPoints>
			<UnitStat_Intelligence>1</UnitStat_Intelligence>
			<UnitStat_Moves>3</UnitStat_Moves>
		</LevelMilestone>
		<LevelMilestone InternalName="L18">
			<Level>18</Level>
			<UnitStat_Accuracy>75</UnitStat_Accuracy>
			<UnitStat_Attack_Pierce>0</UnitStat_Attack_Pierce>
			<UnitStat_ChanceToCrit>1</UnitStat_ChanceToCrit>
			<UnitStat_CombatSpeed>18</UnitStat_CombatSpeed>
			<UnitStat_HitPoints>6</UnitStat_HitPoints>
			<UnitStat_Intelligence>1</UnitStat_Intelligence>
			<UnitStat_Moves>3</UnitStat_Moves>
		</LevelMilestone>
		<LevelMilestone InternalName="L19">
			<Level>19</Level>
			<UnitStat_Accuracy>75</UnitStat_Accuracy>
			<UnitStat_Attack_Pierce>0</UnitStat_Attack_Pierce>
			<UnitStat_ChanceToCrit>1</UnitStat_ChanceToCrit>
			<UnitStat_CombatSpeed>18</UnitStat_CombatSpeed>
			<UnitStat_HitPoints>6</UnitStat_HitPoints>
			<UnitStat_Intelligence>1</UnitStat_Intelligence>
			<UnitStat_Moves>3</UnitStat_Moves>
		</LevelMilestone>
		<LevelMilestone InternalName="L20">
			<Level>20</Level>
			<UnitStat_Accuracy>75</UnitStat_Accuracy>
			<UnitStat_Attack_Pierce>0</UnitStat_Attack_Pierce>
			<UnitStat_ChanceToCrit>1</UnitStat_ChanceToCrit>
			<UnitStat_CombatSpeed>18</UnitStat_CombatSpeed>
			<UnitStat_HitPoints>6</UnitStat_HitPoints>
			<UnitStat_Intelligence>1</UnitStat_Intelligence>
			<UnitStat_Moves>3</UnitStat_Moves>
		</LevelMilestone>
		<SelectedAbilityBonusOption>UndeadImmunities</SelectedAbilityBonusOption>
		<SelectedAbilityBonusOption>Inaccurate</SelectedAbilityBonusOption>
		<SelectedAbilityBonusOption>Ability_X_IsSkeleton</SelectedAbilityBonusOption>
		<Backstory/>
		<Equipment>Club</Equipment>
		<Prereq>
			<Type>AbilityBonusOption</Type>
			<Attribute>ReanimationRituals</Attribute>
			<Target>Player</Target>
		</Prereq>
		<AnimationPack>SkeletonAnimationPack</AnimationPack>
		<AnimationParticleEffect>Awaken,_Skeleton_Awaken,0.0,10.0,0.0,1.5</AnimationParticleEffect>
		<BattleAnimationBehavior>Melee</BattleAnimationBehavior>
		<ClothMapScale>1.5</ClothMapScale>
		<EyeTexture>Eyeblink_F4_Blk.png</EyeTexture>
		<Color_Skin>40,45,50,55</Color_Skin>
		<CutSceneDataPack>DefaultUnitCutscenePack</CutSceneDataPack>
		<InfoCardBackground>BG_BarrenForest</InfoCardBackground>
		<ModelPath>M_Skeleton_Mesh_01.hkb</ModelPath>
		<ModelScale>1</ModelScale>
		<SkeletonPath>K_Male_Skeleton_01.hkb</SkeletonPath>
		<SoundPack>SoundPack_Skeleton</SoundPack>
		<TacticalModelScale>1.5</TacticalModelScale>
		<Texture_Skin>M_Skeleton_Texture_01.png</Texture_Skin>
		<UnitModelType>WraithMale</UnitModelType>
		<AlwaysInTileCenter>1</AlwaysInTileCenter>
		<SelectedAbilityBonusOption>Ability_X_BloodCreatures</SelectedAbilityBonusOption>
	</UnitType>
	<UnitType InternalName="RR_Zombie">
		<DisplayName>Zombies #U</DisplayName>
		<Description>Remains of those long dead, called back to service by necromancers. They are tougher than skeletal reanimates, but not as fast.</Description>
		<CanBeDesigned>1</CanBeDesigned>
		<CreatureType>Undead</CreatureType>
		<AdditionalTrainingTurns>10</AdditionalTrainingTurns>
		<HasWages>0</HasWages>
		<AllowGrouping>1</AllowGrouping>
		<IsSovereign>0</IsSovereign>
		<ProductionRequirement>
			<Type>Resource</Type>
			<Attribute>Mana</Attribute>
			<Value>6.67</Value>
		</ProductionRequirement>
		<LevelMilestone InternalName="L1">
			<Level>1</Level>
			<UnitStat_Accuracy>75</UnitStat_Accuracy>
			<UnitStat_Attack_Pierce>0</UnitStat_Attack_Pierce>
			<UnitStat_ChanceToCrit>1</UnitStat_ChanceToCrit>
			<UnitStat_CombatSpeed>16</UnitStat_CombatSpeed>
			<UnitStat_HitPoints>8</UnitStat_HitPoints>
			<UnitStat_Intelligence>1</UnitStat_Intelligence>
			<UnitStat_Moves>3</UnitStat_Moves>
			<UnitStat_BG_IsHumanoid>1</UnitStat_BG_IsHumanoid>
			<UnitStat_BG_IsRace_Undead>1</UnitStat_BG_IsRace_Undead>
			<UnitStat_BG_IsEmpire>1</UnitStat_BG_IsEmpire>
			<UnitStat_BG_IsImmortal>1</UnitStat_BG_IsImmortal>
			<UnitStat_BG_IsUndead>1</UnitStat_BG_IsUndead>
			<UnitStat_ImmuneToFear>1</UnitStat_ImmuneToFear>
			<UnitStat_BG_IsNotAlive>1</UnitStat_BG_IsNotAlive>
		</LevelMilestone>
		<LevelMilestone InternalName="L2">
			<Level>2</Level>
			<UnitStat_Accuracy>75</UnitStat_Accuracy>
			<UnitStat_Attack_Pierce>0</UnitStat_Attack_Pierce>
			<UnitStat_ChanceToCrit>1</UnitStat_ChanceToCrit>
			<UnitStat_CombatSpeed>16</UnitStat_CombatSpeed>
			<UnitStat_HitPoints>8</UnitStat_HitPoints>
			<UnitStat_Intelligence>1</UnitStat_Intelligence>
			<UnitStat_Moves>3</UnitStat_Moves>
		</LevelMilestone>
		<LevelMilestone InternalName="L3">
			<Level>3</Level>
			<UnitStat_Accuracy>75</UnitStat_Accuracy>
			<UnitStat_Attack_Pierce>0</UnitStat_Attack_Pierce>
			<UnitStat_ChanceToCrit>1</UnitStat_ChanceToCrit>
			<UnitStat_CombatSpeed>16</UnitStat_CombatSpeed>
			<UnitStat_HitPoints>8</UnitStat_HitPoints>
			<UnitStat_Intelligence>1</UnitStat_Intelligence>
			<UnitStat_Moves>3</UnitStat_Moves>
		</LevelMilestone>
		<LevelMilestone InternalName="L4">
			<Level>4</Level>
			<UnitStat_Accuracy>75</UnitStat_Accuracy>
			<UnitStat_Attack_Pierce>0</UnitStat_Attack_Pierce>
			<UnitStat_ChanceToCrit>1</UnitStat_ChanceToCrit>
			<UnitStat_CombatSpeed>16</UnitStat_CombatSpeed>
			<UnitStat_HitPoints>8</UnitStat_HitPoints>
			<UnitStat_Intelligence>1</UnitStat_Intelligence>
			<UnitStat_Moves>3</UnitStat_Moves>
		</LevelMilestone>
		<LevelMilestone InternalName="L5">
			<Level>5</Level>
			<UnitStat_Accuracy>75</UnitStat_Accuracy>
			<UnitStat_Attack_Pierce>0</UnitStat_Attack_Pierce>
			<UnitStat_ChanceToCrit>1</UnitStat_ChanceToCrit>
			<UnitStat_CombatSpeed>16</UnitStat_CombatSpeed>
			<UnitStat_HitPoints>8</UnitStat_HitPoints>
			<UnitStat_Intelligence>1</UnitStat_Intelligence>
			<UnitStat_Moves>3</UnitStat_Moves>
		</LevelMilestone>
		<LevelMilestone InternalName="L6">
			<Level>6</Level>
			<UnitStat_Accuracy>75</UnitStat_Accuracy>
			<UnitStat_Attack_Pierce>0</UnitStat_Attack_Pierce>
			<UnitStat_ChanceToCrit>1</UnitStat_ChanceToCrit>
			<UnitStat_CombatSpeed>16</UnitStat_CombatSpeed>
			<UnitStat_HitPoints>8</UnitStat_HitPoints>
			<UnitStat_Intelligence>1</UnitStat_Intelligence>
			<UnitStat_Moves>3</UnitStat_Moves>
		</LevelMilestone>
		<LevelMilestone InternalName="L7">
			<Level>7</Level>
			<UnitStat_Accuracy>75</UnitStat_Accuracy>
			<UnitStat_Attack_Pierce>0</UnitStat_Attack_Pierce>
			<UnitStat_ChanceToCrit>1</UnitStat_ChanceToCrit>
			<UnitStat_CombatSpeed>16</UnitStat_CombatSpeed>
			<UnitStat_HitPoints>8</UnitStat_HitPoints>
			<UnitStat_Intelligence>1</UnitStat_Intelligence>
			<UnitStat_Moves>3</UnitStat_Moves>
		</LevelMilestone>
		<LevelMilestone InternalName="L8">
			<Level>8</Level>
			<UnitStat_Accuracy>75</UnitStat_Accuracy>
			<UnitStat_Attack_Pierce>0</UnitStat_Attack_Pierce>
			<UnitStat_ChanceToCrit>1</UnitStat_ChanceToCrit>
			<UnitStat_CombatSpeed>16</UnitStat_CombatSpeed>
			<UnitStat_HitPoints>8</UnitStat_HitPoints>
			<UnitStat_Intelligence>1</UnitStat_Intelligence>
			<UnitStat_Moves>3</UnitStat_Moves>
		</LevelMilestone>
		<LevelMilestone InternalName="L9">
			<Level>9</Level>
			<UnitStat_Accuracy>75</UnitStat_Accuracy>
			<UnitStat_Attack_Pierce>0</UnitStat_Attack_Pierce>
			<UnitStat_ChanceToCrit>1</UnitStat_ChanceToCrit>
			<UnitStat_CombatSpeed>16</UnitStat_CombatSpeed>
			<UnitStat_HitPoints>8</UnitStat_HitPoints>
			<UnitStat_Intelligence>1</UnitStat_Intelligence>
			<UnitStat_Moves>3</UnitStat_Moves>
		</LevelMilestone>
		<LevelMilestone InternalName="L10">
			<Level>10</Level>
			<UnitStat_Accuracy>75</UnitStat_Accuracy>
			<UnitStat_Attack_Pierce>0</UnitStat_Attack_Pierce>
			<UnitStat_ChanceToCrit>1</UnitStat_ChanceToCrit>
			<UnitStat_CombatSpeed>16</UnitStat_CombatSpeed>
			<UnitStat_HitPoints>8</UnitStat_HitPoints>
			<UnitStat_Intelligence>1</UnitStat_Intelligence>
			<UnitStat_Moves>3</UnitStat_Moves>
		</LevelMilestone>
		<LevelMilestone InternalName="L11">
			<Level>11</Level>
			<UnitStat_Accuracy>75</UnitStat_Accuracy>
			<UnitStat_Attack_Pierce>0</UnitStat_Attack_Pierce>
			<UnitStat_ChanceToCrit>1</UnitStat_ChanceToCrit>
			<UnitStat_CombatSpeed>16</UnitStat_CombatSpeed>
			<UnitStat_HitPoints>8</UnitStat_HitPoints>
			<UnitStat_Intelligence>1</UnitStat_Intelligence>
			<UnitStat_Moves>3</UnitStat_Moves>
		</LevelMilestone>
		<LevelMilestone InternalName="L12">
			<Level>12</Level>
			<UnitStat_Accuracy>75</UnitStat_Accuracy>
			<UnitStat_Attack_Pierce>0</UnitStat_Attack_Pierce>
			<UnitStat_ChanceToCrit>1</UnitStat_ChanceToCrit>
			<UnitStat_CombatSpeed>16</UnitStat_CombatSpeed>
			<UnitStat_HitPoints>8</UnitStat_HitPoints>
			<UnitStat_Intelligence>1</UnitStat_Intelligence>
			<UnitStat_Moves>3</UnitStat_Moves>
		</LevelMilestone>
		<LevelMilestone InternalName="L13">
			<Level>13</Level>
			<UnitStat_Accuracy>75</UnitStat_Accuracy>
			<UnitStat_Attack_Pierce>0</UnitStat_Attack_Pierce>
			<UnitStat_ChanceToCrit>1</UnitStat_ChanceToCrit>
			<UnitStat_CombatSpeed>16</UnitStat_CombatSpeed>
			<UnitStat_HitPoints>8</UnitStat_HitPoints>
			<UnitStat_Intelligence>1</UnitStat_Intelligence>
			<UnitStat_Moves>3</UnitStat_Moves>
		</LevelMilestone>
		<LevelMilestone InternalName="L14">
			<Level>14</Level>
			<UnitStat_Accuracy>75</UnitStat_Accuracy>
			<UnitStat_Attack_Pierce>0</UnitStat_Attack_Pierce>
			<UnitStat_ChanceToCrit>1</UnitStat_ChanceToCrit>
			<UnitStat_CombatSpeed>16</UnitStat_CombatSpeed>
			<UnitStat_HitPoints>8</UnitStat_HitPoints>
			<UnitStat_Intelligence>1</UnitStat_Intelligence>
			<UnitStat_Moves>3</UnitStat_Moves>
		</LevelMilestone>
		<LevelMilestone InternalName="L15">
			<Level>15</Level>
			<UnitStat_Accuracy>75</UnitStat_Accuracy>
			<UnitStat_Attack_Pierce>0</UnitStat_Attack_Pierce>
			<UnitStat_ChanceToCrit>1</UnitStat_ChanceToCrit>
			<UnitStat_CombatSpeed>16</UnitStat_CombatSpeed>
			<UnitStat_HitPoints>8</UnitStat_HitPoints>
			<UnitStat_Intelligence>1</UnitStat_Intelligence>
			<UnitStat_Moves>3</UnitStat_Moves>
		</LevelMilestone>
		<LevelMilestone InternalName="L16">
			<Level>16</Level>
			<UnitStat_Accuracy>75</UnitStat_Accuracy>
			<UnitStat_Attack_Pierce>0</UnitStat_Attack_Pierce>
			<UnitStat_ChanceToCrit>1</UnitStat_ChanceToCrit>
			<UnitStat_CombatSpeed>16</UnitStat_CombatSpeed>
			<UnitStat_HitPoints>8</UnitStat_HitPoints>
			<UnitStat_Intelligence>1</UnitStat_Intelligence>
			<UnitStat_Moves>3</UnitStat_Moves>
		</LevelMilestone>
		<LevelMilestone InternalName="L17">
			<Level>17</Level>
			<UnitStat_Accuracy>75</UnitStat_Accuracy>
			<UnitStat_Attack_Pierce>0</UnitStat_Attack_Pierce>
			<UnitStat_ChanceToCrit>1</UnitStat_ChanceToCrit>
			<UnitStat_CombatSpeed>16</UnitStat_CombatSpeed>
			<UnitStat_HitPoints>8</UnitStat_HitPoints>
			<UnitStat_Intelligence>1</UnitStat_Intelligence>
			<UnitStat_Moves>3</UnitStat_Moves>
		</LevelMilestone>
		<LevelMilestone InternalName="L18">
			<Level>18</Level>
			<UnitStat_Accuracy>75</UnitStat_Accuracy>
			<UnitStat_Attack_Pierce>0</UnitStat_Attack_Pierce>
			<UnitStat_ChanceToCrit>1</UnitStat_ChanceToCrit>
			<UnitStat_CombatSpeed>16</UnitStat_CombatSpeed>
			<UnitStat_HitPoints>8</UnitStat_HitPoints>
			<UnitStat_Intelligence>1</UnitStat_Intelligence>
			<UnitStat_Moves>3</UnitStat_Moves>
		</LevelMilestone>
		<LevelMilestone InternalName="L19">
			<Level>19</Level>
			<UnitStat_Accuracy>75</UnitStat_Accuracy>
			<UnitStat_Attack_Pierce>0</UnitStat_Attack_Pierce>
			<UnitStat_ChanceToCrit>1</UnitStat_ChanceToCrit>
			<UnitStat_CombatSpeed>16</UnitStat_CombatSpeed>
			<UnitStat_HitPoints>8</UnitStat_HitPoints>
			<UnitStat_Intelligence>1</UnitStat_Intelligence>
			<UnitStat_Moves>3</UnitStat_Moves>
		</LevelMilestone>
		<LevelMilestone InternalName="L20">
			<Level>20</Level>
			<UnitStat_Accuracy>75</UnitStat_Accuracy>
			<UnitStat_Attack_Pierce>0</UnitStat_Attack_Pierce>
			<UnitStat_ChanceToCrit>1</UnitStat_ChanceToCrit>
			<UnitStat_CombatSpeed>16</UnitStat_CombatSpeed>
			<UnitStat_HitPoints>8</UnitStat_HitPoints>
			<UnitStat_Intelligence>1</UnitStat_Intelligence>
			<UnitStat_Moves>3</UnitStat_Moves>
		</LevelMilestone>
		<SelectedAbilityBonusOption>UndeadImmunities</SelectedAbilityBonusOption>
		<SelectedAbilityBonusOption>Inaccurate</SelectedAbilityBonusOption>
		<Prereq>
			<Type>AbilityBonusOption</Type>
			<Attribute>ReanimationRituals</Attribute>
			<Target>Player</Target>
		</Prereq>
		<Equipment>Club</Equipment>
		<Equipment>K_Male_Head_02</Equipment>
		<AnimationPack>SkeletonAnimationPack</AnimationPack>
		<BattleAnimationBehavior>Melee</BattleAnimationBehavior>
		<ClothMapScale>1.6</ClothMapScale>
		<Color_Clothing1>185,173,168,255</Color_Clothing1>
		<Color_Clothing2>185,173,168,255</Color_Clothing2>
		<Color_Hair>50,50,50,255</Color_Hair>
		<Color_Metal>150,155,135,255</Color_Metal>
		<Color_Skin>206,195,181,255</Color_Skin>
		<CutSceneDataPack>SandCrawlerUnitCutscenePack</CutSceneDataPack>
		<EyeTexture>Eyeblink_M_Dead.png</EyeTexture>
		<InfoCardBackground>BG38_Tomb</InfoCardBackground>
		<ModelPath>K_Male_Mesh_01.hkb</ModelPath>
		<ModelScale>1</ModelScale>
		<OnHitParticleName>Bloody_OnHit</OnHitParticleName>
		<SkeletonPath>K_Male_Skeleton_01.hkb</SkeletonPath>
		<SoundPack>SoundPack_Butcherman</SoundPack>
		<TacticalModelScale>1.5</TacticalModelScale>
		<Texture_Eyes>Eyeblink_M_Dead.png</Texture_Eyes>
		<Texture_Skin>K_Male_ButchermanSkin_Texture_01.dds</Texture_Skin>
		<UnitModelType>WraithMale</UnitModelType>
		<AlwaysInTileCenter>1</AlwaysInTileCenter>
		<SelectedAbilityBonusOption>Ability_X_BloodCreatures</SelectedAbilityBonusOption>
	</UnitType>
	<UnitType InternalName="RR_Spectre">
		<DisplayName>Spectre #U</DisplayName>
		<CreatureType>Undead</CreatureType>
		<Description>The disembodied spirit of someone who was murdered in cold blood. Blinded by hatred and jealousy for those still living, and enslaved by the dark magic of necromancy.</Description>
		<CanBeDesigned>1</CanBeDesigned>
		<IsUniqueButBuildable>1</IsUniqueButBuildable>
		<IsSovereign>0</IsSovereign>
		<MovementType>Air</MovementType>
		<AdditionalTrainingTurns>250</AdditionalTrainingTurns>
		<Prereq>
			<Type>Tech</Type>
			<Attribute>Sorcery</Attribute>
		</Prereq>
		<ProductionRequirement>
			<Type>Resource</Type>
			<Attribute>Mana</Attribute>
			<Value>60</Value>
		</ProductionRequirement>
		<ProductionRequirement>
			<Type>Resource</Type>
			<Attribute>RefinedCrystal</Attribute>
			<Value>10</Value>
		</ProductionRequirement>
		<Prereq>
			<Type>AbilityBonusOption</Type>
			<Attribute>ReanimationRituals</Attribute>
			<Target>Player</Target>
		</Prereq>
		<AllowGrouping>0</AllowGrouping>
		<HasWages>0</HasWages>
		<LevelMilestone InternalName="L1">
			<Level>1</Level>
			<UnitStat_Accuracy>75</UnitStat_Accuracy>
			<UnitStat_Attack_Pierce>0</UnitStat_Attack_Pierce>
			<UnitStat_Attack_Cold>9</UnitStat_Attack_Cold>
			<UnitStat_ChanceToCrit>1</UnitStat_ChanceToCrit>
			<UnitStat_CombatSpeed>34</UnitStat_CombatSpeed>
			<UnitStat_HitPoints>15</UnitStat_HitPoints>
			<UnitStat_Moves>4</UnitStat_Moves>
			<UnitStat_BG_IsHumanoid>1</UnitStat_BG_IsHumanoid>
			<UnitStat_BG_IsRace_Undead>1</UnitStat_BG_IsRace_Undead>
			<UnitStat_BG_IsEmpire>1</UnitStat_BG_IsEmpire>
			<UnitStat_BG_IsImmortal>1</UnitStat_BG_IsImmortal>
			<UnitStat_BG_IsUndead>1</UnitStat_BG_IsUndead>
			<UnitStat_ImmuneToFear>1</UnitStat_ImmuneToFear>
			<UnitStat_BG_IsNotAlive>1</UnitStat_BG_IsNotAlive>
			<UnitStat_BG_IsFlying>1</UnitStat_BG_IsFlying>
		</LevelMilestone>
		<LevelMilestone InternalName="L2">
			<Level>2</Level>
			<UnitStat_Accuracy>75</UnitStat_Accuracy>
			<UnitStat_Attack_Pierce>0</UnitStat_Attack_Pierce>
			<UnitStat_Attack_Cold>10</UnitStat_Attack_Cold>
			<UnitStat_ChanceToCrit>1</UnitStat_ChanceToCrit>
			<UnitStat_CombatSpeed>17</UnitStat_CombatSpeed>
			<UnitStat_HitPoints>15</UnitStat_HitPoints>
			<UnitStat_Moves>4</UnitStat_Moves>
			<UnitStat_BG_IsFlying>1</UnitStat_BG_IsFlying>
		</LevelMilestone>
		<LevelMilestone InternalName="L3">
			<Level>3</Level>
			<UnitStat_Accuracy>75</UnitStat_Accuracy>
			<UnitStat_Attack_Pierce>0</UnitStat_Attack_Pierce>
			<UnitStat_Attack_Cold>10</UnitStat_Attack_Cold>
			<UnitStat_ChanceToCrit>1</UnitStat_ChanceToCrit>
			<UnitStat_CombatSpeed>34</UnitStat_CombatSpeed>
			<UnitStat_HitPoints>16</UnitStat_HitPoints>
			<UnitStat_Moves>4</UnitStat_Moves>
			<UnitStat_BG_IsFlying>1</UnitStat_BG_IsFlying>
		</LevelMilestone>
		<LevelMilestone InternalName="L4">
			<Level>4</Level>
			<UnitStat_Accuracy>75</UnitStat_Accuracy>
			<UnitStat_Attack_Pierce>0</UnitStat_Attack_Pierce>
			<UnitStat_Attack_Cold>11</UnitStat_Attack_Cold>
			<UnitStat_ChanceToCrit>1</UnitStat_ChanceToCrit>
			<UnitStat_CombatSpeed>37</UnitStat_CombatSpeed>
			<UnitStat_HitPoints>16</UnitStat_HitPoints>
			<UnitStat_Moves>4</UnitStat_Moves>
			<UnitStat_BG_IsFlying>1</UnitStat_BG_IsFlying>
		</LevelMilestone>
		<LevelMilestone InternalName="L5">
			<Level>5</Level>
			<UnitStat_Accuracy>75</UnitStat_Accuracy>
			<UnitStat_Attack_Pierce>0</UnitStat_Attack_Pierce>
			<UnitStat_Attack_Cold>11</UnitStat_Attack_Cold>
			<UnitStat_ChanceToCrit>2</UnitStat_ChanceToCrit>
			<UnitStat_CombatSpeed>38</UnitStat_CombatSpeed>
			<UnitStat_HitPoints>17</UnitStat_HitPoints>
			<UnitStat_Moves>4</UnitStat_Moves>
			<UnitStat_BG_IsFlying>1</UnitStat_BG_IsFlying>
		</LevelMilestone>
		<LevelMilestone InternalName="L6">
			<Level>6</Level>
			<UnitStat_Accuracy>75</UnitStat_Accuracy>
			<UnitStat_Attack_Pierce>0</UnitStat_Attack_Pierce>
			<UnitStat_Attack_Cold>12</UnitStat_Attack_Cold>
			<UnitStat_ChanceToCrit>2</UnitStat_ChanceToCrit>
			<UnitStat_CombatSpeed>39</UnitStat_CombatSpeed>
			<UnitStat_HitPoints>17</UnitStat_HitPoints>
			<UnitStat_Moves>4</UnitStat_Moves>
			<UnitStat_BG_IsFlying>1</UnitStat_BG_IsFlying>
		</LevelMilestone>
		<LevelMilestone InternalName="L7">
			<Level>7</Level>
			<UnitStat_Accuracy>75</UnitStat_Accuracy>
			<UnitStat_Attack_Pierce>0</UnitStat_Attack_Pierce>
			<UnitStat_Attack_Cold>12</UnitStat_Attack_Cold>
			<UnitStat_ChanceToCrit>2</UnitStat_ChanceToCrit>
			<UnitStat_CombatSpeed>40</UnitStat_CombatSpeed>
			<UnitStat_HitPoints>18</UnitStat_HitPoints>
			<UnitStat_Moves>4</UnitStat_Moves>
			<UnitStat_BG_IsFlying>1</UnitStat_BG_IsFlying>
		</LevelMilestone>
		<LevelMilestone InternalName="L8">
			<Level>8</Level>
			<UnitStat_Accuracy>75</UnitStat_Accuracy>
			<UnitStat_Attack_Pierce>0</UnitStat_Attack_Pierce>
			<UnitStat_Attack_Cold>13</UnitStat_Attack_Cold>
			<UnitStat_ChanceToCrit>2</UnitStat_ChanceToCrit>
			<UnitStat_CombatSpeed>41</UnitStat_CombatSpeed>
			<UnitStat_HitPoints>18</UnitStat_HitPoints>
			<UnitStat_Moves>4</UnitStat_Moves>
			<UnitStat_BG_IsFlying>1</UnitStat_BG_IsFlying>
		</LevelMilestone>
		<LevelMilestone InternalName="L9">
			<Level>9</Level>
			<UnitStat_Accuracy>75</UnitStat_Accuracy>
			<UnitStat_Attack_Pierce>0</UnitStat_Attack_Pierce>
			<UnitStat_Attack_Cold>13</UnitStat_Attack_Cold>
			<UnitStat_ChanceToCrit>2</UnitStat_ChanceToCrit>
			<UnitStat_CombatSpeed>42</UnitStat_CombatSpeed>
			<UnitStat_HitPoints>19</UnitStat_HitPoints>
			<UnitStat_Moves>4</UnitStat_Moves>
			<UnitStat_BG_IsFlying>1</UnitStat_BG_IsFlying>
		</LevelMilestone>
		<LevelMilestone InternalName="L10">
			<Level>10</Level>
			<UnitStat_Accuracy>75</UnitStat_Accuracy>
			<UnitStat_Attack_Pierce>0</UnitStat_Attack_Pierce>
			<UnitStat_Attack_Cold>14</UnitStat_Attack_Cold>
			<UnitStat_ChanceToCrit>4</UnitStat_ChanceToCrit>
			<UnitStat_CombatSpeed>43</UnitStat_CombatSpeed>
			<UnitStat_HitPoints>19</UnitStat_HitPoints>
			<UnitStat_Moves>4</UnitStat_Moves>
			<UnitStat_BG_IsFlying>1</UnitStat_BG_IsFlying>
		</LevelMilestone>
		<LevelMilestone InternalName="L11">
			<Level>11</Level>
			<UnitStat_Accuracy>75</UnitStat_Accuracy>
			<UnitStat_Attack_Pierce>0</UnitStat_Attack_Pierce>
			<UnitStat_Attack_Cold>14</UnitStat_Attack_Cold>
			<UnitStat_ChanceToCrit>4</UnitStat_ChanceToCrit>
			<UnitStat_CombatSpeed>44</UnitStat_CombatSpeed>
			<UnitStat_HitPoints>20</UnitStat_HitPoints>
			<UnitStat_Moves>4</UnitStat_Moves>
			<UnitStat_BG_IsFlying>1</UnitStat_BG_IsFlying>
		</LevelMilestone>
		<LevelMilestone InternalName="L12">
			<Level>12</Level>
			<UnitStat_Accuracy>75</UnitStat_Accuracy>
			<UnitStat_Attack_Pierce>0</UnitStat_Attack_Pierce>
			<UnitStat_Attack_Cold>15</UnitStat_Attack_Cold>
			<UnitStat_ChanceToCrit>4</UnitStat_ChanceToCrit>
			<UnitStat_CombatSpeed>45</UnitStat_CombatSpeed>
			<UnitStat_HitPoints>20</UnitStat_HitPoints>
			<UnitStat_Moves>4</UnitStat_Moves>
			<UnitStat_BG_IsFlying>1</UnitStat_BG_IsFlying>
		</LevelMilestone>
		<LevelMilestone InternalName="L13">
			<Level>13</Level>
			<UnitStat_Accuracy>75</UnitStat_Accuracy>
			<UnitStat_Attack_Pierce>0</UnitStat_Attack_Pierce>
			<UnitStat_Attack_Cold>15</UnitStat_Attack_Cold>
			<UnitStat_ChanceToCrit>4</UnitStat_ChanceToCrit>
			<UnitStat_CombatSpeed>46</UnitStat_CombatSpeed>
			<UnitStat_HitPoints>21</UnitStat_HitPoints>
			<UnitStat_Moves>4</UnitStat_Moves>
			<UnitStat_BG_IsFlying>1</UnitStat_BG_IsFlying>
		</LevelMilestone>
		<LevelMilestone InternalName="L14">
			<Level>14</Level>
			<UnitStat_Accuracy>75</UnitStat_Accuracy>
			<UnitStat_Attack_Pierce>0</UnitStat_Attack_Pierce>
			<UnitStat_Attack_Cold>16</UnitStat_Attack_Cold>
			<UnitStat_ChanceToCrit>4</UnitStat_ChanceToCrit>
			<UnitStat_CombatSpeed>47</UnitStat_CombatSpeed>
			<UnitStat_HitPoints>21</UnitStat_HitPoints>
			<UnitStat_Moves>4</UnitStat_Moves>
			<UnitStat_BG_IsFlying>1</UnitStat_BG_IsFlying>
		</LevelMilestone>
		<LevelMilestone InternalName="L15">
			<Level>15</Level>
			<UnitStat_Accuracy>75</UnitStat_Accuracy>
			<UnitStat_Attack_Pierce>0</UnitStat_Attack_Pierce>
			<UnitStat_Attack_Cold>16</UnitStat_Attack_Cold>
			<UnitStat_ChanceToCrit>8</UnitStat_ChanceToCrit>
			<UnitStat_CombatSpeed>48</UnitStat_CombatSpeed>
			<UnitStat_HitPoints>22</UnitStat_HitPoints>
			<UnitStat_Moves>4</UnitStat_Moves>
			<UnitStat_BG_IsFlying>1</UnitStat_BG_IsFlying>
		</LevelMilestone>
		<LevelMilestone InternalName="L16">
			<Level>16</Level>
			<UnitStat_Accuracy>75</UnitStat_Accuracy>
			<UnitStat_Attack_Pierce>0</UnitStat_Attack_Pierce>
			<UnitStat_Attack_Cold>17</UnitStat_Attack_Cold>
			<UnitStat_ChanceToCrit>8</UnitStat_ChanceToCrit>
			<UnitStat_CombatSpeed>49</UnitStat_CombatSpeed>
			<UnitStat_HitPoints>22</UnitStat_HitPoints>
			<UnitStat_Moves>4</UnitStat_Moves>
			<UnitStat_BG_IsFlying>1</UnitStat_BG_IsFlying>
		</LevelMilestone>
		<LevelMilestone InternalName="L17">
			<Level>17</Level>
			<UnitStat_Accuracy>75</UnitStat_Accuracy>
			<UnitStat_Attack_Pierce>0</UnitStat_Attack_Pierce>
			<UnitStat_Attack_Cold>17</UnitStat_Attack_Cold>
			<UnitStat_ChanceToCrit>8</UnitStat_ChanceToCrit>
			<UnitStat_CombatSpeed>50</UnitStat_CombatSpeed>
			<UnitStat_HitPoints>23</UnitStat_HitPoints>
			<UnitStat_Moves>4</UnitStat_Moves>
			<UnitStat_BG_IsFlying>1</UnitStat_BG_IsFlying>
		</LevelMilestone>
		<LevelMilestone InternalName="L18">
			<Level>18</Level>
			<UnitStat_Accuracy>75</UnitStat_Accuracy>
			<UnitStat_Attack_Pierce>0</UnitStat_Attack_Pierce>
			<UnitStat_Attack_Cold>18</UnitStat_Attack_Cold>
			<UnitStat_ChanceToCrit>8</UnitStat_ChanceToCrit>
			<UnitStat_CombatSpeed>51</UnitStat_CombatSpeed>
			<UnitStat_HitPoints>23</UnitStat_HitPoints>
			<UnitStat_Moves>4</UnitStat_Moves>
			<UnitStat_BG_IsFlying>1</UnitStat_BG_IsFlying>
		</LevelMilestone>
		<LevelMilestone InternalName="L19">
			<Level>19</Level>
			<UnitStat_Accuracy>75</UnitStat_Accuracy>
			<UnitStat_Attack_Pierce>0</UnitStat_Attack_Pierce>
			<UnitStat_Attack_Cold>18</UnitStat_Attack_Cold>
			<UnitStat_ChanceToCrit>8</UnitStat_ChanceToCrit>
			<UnitStat_CombatSpeed>52</UnitStat_CombatSpeed>
			<UnitStat_HitPoints>24</UnitStat_HitPoints>
			<UnitStat_Moves>4</UnitStat_Moves>
			<UnitStat_BG_IsFlying>1</UnitStat_BG_IsFlying>
		</LevelMilestone>
		<LevelMilestone InternalName="L20">
			<Level>20</Level>
			<UnitStat_Accuracy>75</UnitStat_Accuracy>
			<UnitStat_Attack_Pierce>0</UnitStat_Attack_Pierce>
			<UnitStat_Attack_Cold>19</UnitStat_Attack_Cold>
			<UnitStat_ChanceToCrit>16</UnitStat_ChanceToCrit>
			<UnitStat_CombatSpeed>53</UnitStat_CombatSpeed>
			<UnitStat_HitPoints>24</UnitStat_HitPoints>
			<UnitStat_Moves>4</UnitStat_Moves>
			<UnitStat_BG_IsFlying>1</UnitStat_BG_IsFlying>
		</LevelMilestone>
		<SelectedAbilityBonusOption>UndeadImmunities</SelectedAbilityBonusOption>
		<SelectedAbilityBonusOption>Flying</SelectedAbilityBonusOption>
		<SelectedAbilityBonusOption>SemiCorporeal</SelectedAbilityBonusOption>
		<SelectedAbilityBonusOption>SpectreAttackAbilities</SelectedAbilityBonusOption>
		<Medallions InternalName="">
			<All>NR_Disembodied.png</All>
		</Medallions>
		<AnimationPack>BansheeAnimationPack</AnimationPack>
		<BattleAnimationBehavior>Melee</BattleAnimationBehavior>
		<ClothMapScale>1.6</ClothMapScale>
		<Color_Skin>0,0,0,0</Color_Skin>
		<CutSceneDataPack>DefaultUnitAnimationPack</CutSceneDataPack>
		<EyeTexture>Eyeblink_F4_Blk.png</EyeTexture>
		<InfoCardBackground>BG29_Swamp</InfoCardBackground>
		<ModelPath>M_Skeleton_Mesh_01.hkb</ModelPath>
		<ModelScale>1</ModelScale>
		<SkeletonPath>K_Male_Skeleton_01.hkb</SkeletonPath>
		<SoundPack>SoundPack_Banshee</SoundPack>
		<TacticalModelScale>1.5</TacticalModelScale>
		<Texture_Eyes>Eyeblink_Banshee.png</Texture_Eyes>
		<Texture_Trans>M_Skeleton_Texture_01.png</Texture_Trans>
		<UnitModelType>WraithFemale</UnitModelType>
		<EffectAttachment>
			<Attachment>chest_center_Lcf</Attachment>
			<EffectName>A_DeathDemon_Stomach_Particle_01</EffectName>
			<EffectPosition>0,0,0</EffectPosition>
			<EffectRotation>0,0,0</EffectRotation>
			<EffectScale>0.35</EffectScale>
		</EffectAttachment>
		<EffectAttachment>
			<Attachment>shoulder_left_Lcf</Attachment>
			<EffectName>A_DeathDemon_Shoulder_Particle_01</EffectName>
			<EffectPosition>0,0,0</EffectPosition>
			<EffectRotation>0,0,0</EffectRotation>
			<EffectScale>0.2</EffectScale>
		</EffectAttachment>
		<EffectAttachment>
			<Attachment>shoulder_right_Lcf</Attachment>
			<EffectName>A_DeathDemon_Shoulder_Particle_01</EffectName>
			<EffectPosition>0,0,0</EffectPosition>
			<EffectRotation>0,0,0</EffectRotation>
			<EffectScale>0.2</EffectScale>
		</EffectAttachment>
		<EffectAttachment>
			<Attachment>hand_left_Lcf</Attachment>
			<EffectName>A_BlueFire_Particle_02</EffectName>
			<EffectPosition>0,0,0</EffectPosition>
			<EffectRotation>0,0,0</EffectRotation>
			<EffectScale>0.15</EffectScale>
		</EffectAttachment>
		<EffectAttachment>
			<Attachment>hand_right_Lcf</Attachment>
			<EffectName>A_BlueFire_Particle_02</EffectName>
			<EffectPosition>0,0,0</EffectPosition>
			<EffectRotation>0,0,0</EffectRotation>
			<EffectScale>0.15</EffectScale>
		</EffectAttachment>
		<EffectAttachment>
			<Attachment>foot_left_Lcf</Attachment>
			<EffectName>A_BlueFire_Particle_02</EffectName>
			<EffectPosition>0,0,0</EffectPosition>
			<EffectRotation>0,0,0</EffectRotation>
			<EffectScale>0.25</EffectScale>
		</EffectAttachment>
		<EffectAttachment>
			<Attachment>foot_right_Lcf</Attachment>
			<EffectName>A_BlueFire_Particle_02</EffectName>
			<EffectPosition>0,0,0</EffectPosition>
			<EffectRotation>0,0,0</EffectRotation>
			<EffectScale>0.25</EffectScale>
		</EffectAttachment>
		<AlwaysInTileCenter>1</AlwaysInTileCenter>
	</UnitType>
	<UnitType InternalName="RR_Lich">
		<DisplayName>Lich #U</DisplayName>
		<CreatureType>Undead</CreatureType>
		<Description>High ranking members of a death cult who underwent a suicidal ritual to be reborn as a powerful undead spellcaster.</Description>
		<CanBeDesigned>1</CanBeDesigned>
		<AdditionalTrainingTurns>425</AdditionalTrainingTurns>
		<IsSovereign>0</IsSovereign>
		<AllowGrouping>0</AllowGrouping>
		<HasWages>0</HasWages>
		<Prereq>
			<Type>AbilityBonusOption</Type>
			<Attribute>ReanimationRituals</Attribute>
			<Target>Player</Target>
		</Prereq>
		<Prereq>
			<Type>Tech</Type>
			<Attribute>Third_Book_Of_The_Magi</Attribute>
		</Prereq>
		<ProductionRequirement>
			<Type>Resource</Type>
			<Attribute>Mana</Attribute>
			<Value>180</Value>
		</ProductionRequirement>
		<ProductionRequirement>
			<Type>Resource</Type>
			<Attribute>RefinedCrystal</Attribute>
			<Value>15</Value>
		</ProductionRequirement>
		<LevelMilestone InternalName="L1">
			<Level>1</Level>
			<UnitStat_MagicResist>0</UnitStat_MagicResist>
			<UnitStat_MagicPower>70</UnitStat_MagicPower>
			<UnitStat_SpellDamage>0</UnitStat_SpellDamage>
			<UnitStat_Accuracy>75</UnitStat_Accuracy>
			<UnitStat_Attack_Pierce>0</UnitStat_Attack_Pierce>
			<UnitStat_ChanceToCrit>1</UnitStat_ChanceToCrit>
			<UnitStat_CombatSpeed>18</UnitStat_CombatSpeed>
			<UnitStat_Defense_Pierce>12</UnitStat_Defense_Pierce>
			<UnitStat_HitPoints>6</UnitStat_HitPoints>
			<UnitStat_Intelligence>1</UnitStat_Intelligence>
			<UnitStat_Moves>3</UnitStat_Moves>
			<UnitStat_PathOfTheNecro>1</UnitStat_PathOfTheNecro>
			<UnitStat_BG_IsHumanoid>1</UnitStat_BG_IsHumanoid>
			<UnitStat_BG_IsRace_Undead>1</UnitStat_BG_IsRace_Undead>
			<UnitStat_BG_IsEmpire>1</UnitStat_BG_IsEmpire>
			<UnitStat_BG_IsImmortal>1</UnitStat_BG_IsImmortal>
			<UnitStat_BG_IsUndead>1</UnitStat_BG_IsUndead>
			<UnitStat_ImmuneToFear>1</UnitStat_ImmuneToFear>
			<UnitStat_BG_IsNotAlive>1</UnitStat_BG_IsNotAlive>
		</LevelMilestone>
		<LevelMilestone InternalName="L2">
			<Level>2</Level>
			<UnitStat_MagicResist>5</UnitStat_MagicResist>
			<UnitStat_MagicPower>73</UnitStat_MagicPower>
			<UnitStat_SpellDamage>2</UnitStat_SpellDamage>
			<UnitStat_Accuracy>75</UnitStat_Accuracy>
			<UnitStat_Attack_Pierce>0</UnitStat_Attack_Pierce>
			<UnitStat_ChanceToCrit>1</UnitStat_ChanceToCrit>
			<UnitStat_CombatSpeed>18</UnitStat_CombatSpeed>
			<UnitStat_Defense_Pierce>12</UnitStat_Defense_Pierce>
			<UnitStat_HitPoints>6</UnitStat_HitPoints>
			<UnitStat_Intelligence>1</UnitStat_Intelligence>
			<UnitStat_Moves>3</UnitStat_Moves>
			<UnitStat_PathOfTheNecro>1</UnitStat_PathOfTheNecro>
		</LevelMilestone>
		<LevelMilestone InternalName="L3">
			<Level>3</Level>
			<UnitStat_MagicResist>10</UnitStat_MagicResist>
			<UnitStat_MagicPower>73</UnitStat_MagicPower>
			<UnitStat_SpellDamage>4</UnitStat_SpellDamage>
			<UnitStat_Accuracy>75</UnitStat_Accuracy>
			<UnitStat_Attack_Pierce>0</UnitStat_Attack_Pierce>
			<UnitStat_ChanceToCrit>1</UnitStat_ChanceToCrit>
			<UnitStat_CombatSpeed>18</UnitStat_CombatSpeed>
			<UnitStat_Defense_Pierce>12</UnitStat_Defense_Pierce>
			<UnitStat_HitPoints>6</UnitStat_HitPoints>
			<UnitStat_Intelligence>1</UnitStat_Intelligence>
			<UnitStat_Moves>3</UnitStat_Moves>
			<UnitStat_PathOfTheNecro>1</UnitStat_PathOfTheNecro>
		</LevelMilestone>
		<LevelMilestone InternalName="L4">
			<Level>4</Level>
			<UnitStat_MagicResist>15</UnitStat_MagicResist>
			<UnitStat_MagicPower>76</UnitStat_MagicPower>
			<UnitStat_SpellDamage>6</UnitStat_SpellDamage>
			<UnitStat_Accuracy>75</UnitStat_Accuracy>
			<UnitStat_Attack_Pierce>0</UnitStat_Attack_Pierce>
			<UnitStat_ChanceToCrit>1</UnitStat_ChanceToCrit>
			<UnitStat_CombatSpeed>18</UnitStat_CombatSpeed>
			<UnitStat_Defense_Pierce>12</UnitStat_Defense_Pierce>
			<UnitStat_HitPoints>6</UnitStat_HitPoints>
			<UnitStat_Intelligence>1</UnitStat_Intelligence>
			<UnitStat_Moves>3</UnitStat_Moves>
			<UnitStat_PathOfTheNecro>1</UnitStat_PathOfTheNecro>
		</LevelMilestone>
		<LevelMilestone InternalName="L5">
			<Level>5</Level>
			<UnitStat_MagicResist>20</UnitStat_MagicResist>
			<UnitStat_MagicPower>76</UnitStat_MagicPower>
			<UnitStat_SpellDamage>8</UnitStat_SpellDamage>
			<UnitStat_Accuracy>75</UnitStat_Accuracy>
			<UnitStat_Attack_Pierce>0</UnitStat_Attack_Pierce>
			<UnitStat_ChanceToCrit>1</UnitStat_ChanceToCrit>
			<UnitStat_CombatSpeed>18</UnitStat_CombatSpeed>
			<UnitStat_Defense_Pierce>12</UnitStat_Defense_Pierce>
			<UnitStat_HitPoints>6</UnitStat_HitPoints>
			<UnitStat_Intelligence>1</UnitStat_Intelligence>
			<UnitStat_Moves>3</UnitStat_Moves>
			<UnitStat_PathOfTheNecro>1</UnitStat_PathOfTheNecro>
		</LevelMilestone>
		<LevelMilestone InternalName="L6">
			<Level>6</Level>
			<UnitStat_MagicResist>25</UnitStat_MagicResist>
			<UnitStat_MagicPower>79</UnitStat_MagicPower>
			<UnitStat_SpellDamage>10</UnitStat_SpellDamage>
			<UnitStat_Accuracy>75</UnitStat_Accuracy>
			<UnitStat_Attack_Pierce>0</UnitStat_Attack_Pierce>
			<UnitStat_ChanceToCrit>1</UnitStat_ChanceToCrit>
			<UnitStat_CombatSpeed>18</UnitStat_CombatSpeed>
			<UnitStat_Defense_Pierce>12</UnitStat_Defense_Pierce>
			<UnitStat_HitPoints>6</UnitStat_HitPoints>
			<UnitStat_Intelligence>1</UnitStat_Intelligence>
			<UnitStat_Moves>3</UnitStat_Moves>
			<UnitStat_PathOfTheNecro>1</UnitStat_PathOfTheNecro>
		</LevelMilestone>
		<LevelMilestone InternalName="L7">
			<Level>7</Level>
			<UnitStat_MagicResist>30</UnitStat_MagicResist>
			<UnitStat_MagicPower>79</UnitStat_MagicPower>
			<UnitStat_SpellDamage>15</UnitStat_SpellDamage>
			<UnitStat_Accuracy>75</UnitStat_Accuracy>
			<UnitStat_Attack_Pierce>0</UnitStat_Attack_Pierce>
			<UnitStat_ChanceToCrit>1</UnitStat_ChanceToCrit>
			<UnitStat_CombatSpeed>18</UnitStat_CombatSpeed>
			<UnitStat_Defense_Pierce>12</UnitStat_Defense_Pierce>
			<UnitStat_HitPoints>6</UnitStat_HitPoints>
			<UnitStat_Intelligence>1</UnitStat_Intelligence>
			<UnitStat_Moves>3</UnitStat_Moves>
			<UnitStat_PathOfTheNecro>1</UnitStat_PathOfTheNecro>
		</LevelMilestone>
		<LevelMilestone InternalName="L8">
			<Level>8</Level>
			<UnitStat_MagicResist>30</UnitStat_MagicResist>
			<UnitStat_MagicPower>82</UnitStat_MagicPower>
			<UnitStat_SpellDamage>20</UnitStat_SpellDamage>
			<UnitStat_Accuracy>75</UnitStat_Accuracy>
			<UnitStat_Attack_Pierce>0</UnitStat_Attack_Pierce>
			<UnitStat_ChanceToCrit>1</UnitStat_ChanceToCrit>
			<UnitStat_CombatSpeed>18</UnitStat_CombatSpeed>
			<UnitStat_Defense_Pierce>12</UnitStat_Defense_Pierce>
			<UnitStat_HitPoints>6</UnitStat_HitPoints>
			<UnitStat_Intelligence>1</UnitStat_Intelligence>
			<UnitStat_Moves>3</UnitStat_Moves>
			<UnitStat_PathOfTheNecro>1</UnitStat_PathOfTheNecro>
		</LevelMilestone>
		<LevelMilestone InternalName="L9">
			<Level>9</Level>
			<UnitStat_MagicResist>35</UnitStat_MagicResist>
			<UnitStat_MagicPower>82</UnitStat_MagicPower>
			<UnitStat_SpellDamage>25</UnitStat_SpellDamage>
			<UnitStat_Accuracy>75</UnitStat_Accuracy>
			<UnitStat_Attack_Pierce>0</UnitStat_Attack_Pierce>
			<UnitStat_ChanceToCrit>1</UnitStat_ChanceToCrit>
			<UnitStat_CombatSpeed>18</UnitStat_CombatSpeed>
			<UnitStat_Defense_Pierce>12</UnitStat_Defense_Pierce>
			<UnitStat_HitPoints>6</UnitStat_HitPoints>
			<UnitStat_Intelligence>1</UnitStat_Intelligence>
			<UnitStat_Moves>3</UnitStat_Moves>
			<UnitStat_PathOfTheNecro>1</UnitStat_PathOfTheNecro>
		</LevelMilestone>
		<LevelMilestone InternalName="L10">
			<Level>10</Level>
			<UnitStat_MagicResist>35</UnitStat_MagicResist>
			<UnitStat_MagicPower>85</UnitStat_MagicPower>
			<UnitStat_SpellDamage>30</UnitStat_SpellDamage>
			<UnitStat_Accuracy>75</UnitStat_Accuracy>
			<UnitStat_Attack_Pierce>0</UnitStat_Attack_Pierce>
			<UnitStat_ChanceToCrit>1</UnitStat_ChanceToCrit>
			<UnitStat_CombatSpeed>18</UnitStat_CombatSpeed>
			<UnitStat_Defense_Pierce>12</UnitStat_Defense_Pierce>
			<UnitStat_HitPoints>6</UnitStat_HitPoints>
			<UnitStat_Intelligence>1</UnitStat_Intelligence>
			<UnitStat_Moves>3</UnitStat_Moves>
			<UnitStat_PathOfTheNecro>1</UnitStat_PathOfTheNecro>
		</LevelMilestone>
		<LevelMilestone InternalName="L11">
			<Level>11</Level>
			<UnitStat_MagicResist>40</UnitStat_MagicResist>
			<UnitStat_MagicPower>85</UnitStat_MagicPower>
			<UnitStat_SpellDamage>35</UnitStat_SpellDamage>
			<UnitStat_Accuracy>75</UnitStat_Accuracy>
			<UnitStat_Attack_Pierce>0</UnitStat_Attack_Pierce>
			<UnitStat_ChanceToCrit>1</UnitStat_ChanceToCrit>
			<UnitStat_CombatSpeed>18</UnitStat_CombatSpeed>
			<UnitStat_Defense_Pierce>12</UnitStat_Defense_Pierce>
			<UnitStat_HitPoints>6</UnitStat_HitPoints>
			<UnitStat_Intelligence>1</UnitStat_Intelligence>
			<UnitStat_Moves>3</UnitStat_Moves>
			<UnitStat_PathOfTheNecro>1</UnitStat_PathOfTheNecro>
		</LevelMilestone>
		<LevelMilestone InternalName="L12">
			<Level>12</Level>
			<UnitStat_MagicResist>40</UnitStat_MagicResist>
			<UnitStat_MagicPower>88</UnitStat_MagicPower>
			<UnitStat_SpellDamage>40</UnitStat_SpellDamage>
			<UnitStat_Accuracy>75</UnitStat_Accuracy>
			<UnitStat_Attack_Pierce>0</UnitStat_Attack_Pierce>
			<UnitStat_ChanceToCrit>1</UnitStat_ChanceToCrit>
			<UnitStat_CombatSpeed>18</UnitStat_CombatSpeed>
			<UnitStat_Defense_Pierce>12</UnitStat_Defense_Pierce>
			<UnitStat_HitPoints>6</UnitStat_HitPoints>
			<UnitStat_Intelligence>1</UnitStat_Intelligence>
			<UnitStat_Moves>3</UnitStat_Moves>
			<UnitStat_PathOfTheNecro>1</UnitStat_PathOfTheNecro>
		</LevelMilestone>
		<LevelMilestone InternalName="L13">
			<Level>13</Level>
			<UnitStat_MagicResist>45</UnitStat_MagicResist>
			<UnitStat_MagicPower>88</UnitStat_MagicPower>
			<UnitStat_SpellDamage>40</UnitStat_SpellDamage>
			<UnitStat_Accuracy>75</UnitStat_Accuracy>
			<UnitStat_Attack_Pierce>0</UnitStat_Attack_Pierce>
			<UnitStat_ChanceToCrit>1</UnitStat_ChanceToCrit>
			<UnitStat_CombatSpeed>18</UnitStat_CombatSpeed>
			<UnitStat_Defense_Pierce>12</UnitStat_Defense_Pierce>
			<UnitStat_HitPoints>6</UnitStat_HitPoints>
			<UnitStat_Intelligence>1</UnitStat_Intelligence>
			<UnitStat_Moves>3</UnitStat_Moves>
			<UnitStat_PathOfTheNecro>1</UnitStat_PathOfTheNecro>
		</LevelMilestone>
		<LevelMilestone InternalName="L14">
			<Level>14</Level>
			<UnitStat_MagicResist>45</UnitStat_MagicResist>
			<UnitStat_MagicPower>91</UnitStat_MagicPower>
			<UnitStat_SpellDamage>45</UnitStat_SpellDamage>
			<UnitStat_Accuracy>75</UnitStat_Accuracy>
			<UnitStat_Attack_Pierce>0</UnitStat_Attack_Pierce>
			<UnitStat_ChanceToCrit>1</UnitStat_ChanceToCrit>
			<UnitStat_CombatSpeed>18</UnitStat_CombatSpeed>
			<UnitStat_Defense_Pierce>12</UnitStat_Defense_Pierce>
			<UnitStat_HitPoints>6</UnitStat_HitPoints>
			<UnitStat_Intelligence>1</UnitStat_Intelligence>
			<UnitStat_Moves>3</UnitStat_Moves>
			<UnitStat_PathOfTheNecro>1</UnitStat_PathOfTheNecro>
		</LevelMilestone>
		<LevelMilestone InternalName="L15">
			<Level>15</Level>
			<UnitStat_MagicResist>50</UnitStat_MagicResist>
			<UnitStat_MagicPower>91</UnitStat_MagicPower>
			<UnitStat_SpellDamage>50</UnitStat_SpellDamage>
			<UnitStat_Accuracy>75</UnitStat_Accuracy>
			<UnitStat_Attack_Pierce>0</UnitStat_Attack_Pierce>
			<UnitStat_ChanceToCrit>1</UnitStat_ChanceToCrit>
			<UnitStat_CombatSpeed>18</UnitStat_CombatSpeed>
			<UnitStat_Defense_Pierce>12</UnitStat_Defense_Pierce>
			<UnitStat_HitPoints>6</UnitStat_HitPoints>
			<UnitStat_Intelligence>1</UnitStat_Intelligence>
			<UnitStat_Moves>3</UnitStat_Moves>
			<UnitStat_PathOfTheNecro>1</UnitStat_PathOfTheNecro>
		</LevelMilestone>
		<LevelMilestone InternalName="L16">
			<Level>16</Level>
			<UnitStat_MagicResist>50</UnitStat_MagicResist>
			<UnitStat_MagicPower>94</UnitStat_MagicPower>
			<UnitStat_SpellDamage>50</UnitStat_SpellDamage>
			<UnitStat_Accuracy>75</UnitStat_Accuracy>
			<UnitStat_Attack_Pierce>0</UnitStat_Attack_Pierce>
			<UnitStat_ChanceToCrit>1</UnitStat_ChanceToCrit>
			<UnitStat_CombatSpeed>18</UnitStat_CombatSpeed>
			<UnitStat_Defense_Pierce>12</UnitStat_Defense_Pierce>
			<UnitStat_HitPoints>6</UnitStat_HitPoints>
			<UnitStat_Intelligence>1</UnitStat_Intelligence>
			<UnitStat_Moves>3</UnitStat_Moves>
			<UnitStat_PathOfTheNecro>1</UnitStat_PathOfTheNecro>
		</LevelMilestone>
		<LevelMilestone InternalName="L17">
			<Level>17</Level>
			<UnitStat_MagicResist>55</UnitStat_MagicResist>
			<UnitStat_MagicPower>94</UnitStat_MagicPower>
			<UnitStat_SpellDamage>55</UnitStat_SpellDamage>
			<UnitStat_Accuracy>75</UnitStat_Accuracy>
			<UnitStat_Attack_Pierce>0</UnitStat_Attack_Pierce>
			<UnitStat_ChanceToCrit>1</UnitStat_ChanceToCrit>
			<UnitStat_CombatSpeed>18</UnitStat_CombatSpeed>
			<UnitStat_Defense_Pierce>12</UnitStat_Defense_Pierce>
			<UnitStat_HitPoints>6</UnitStat_HitPoints>
			<UnitStat_Intelligence>1</UnitStat_Intelligence>
			<UnitStat_Moves>3</UnitStat_Moves>
			<UnitStat_PathOfTheNecro>1</UnitStat_PathOfTheNecro>
		</LevelMilestone>
		<LevelMilestone InternalName="L18">
			<Level>18</Level>
			<UnitStat_MagicResist>55</UnitStat_MagicResist>
			<UnitStat_MagicPower>97</UnitStat_MagicPower>
			<UnitStat_SpellDamage>55</UnitStat_SpellDamage>
			<UnitStat_Accuracy>75</UnitStat_Accuracy>
			<UnitStat_Attack_Pierce>0</UnitStat_Attack_Pierce>
			<UnitStat_ChanceToCrit>1</UnitStat_ChanceToCrit>
			<UnitStat_CombatSpeed>18</UnitStat_CombatSpeed>
			<UnitStat_Defense_Pierce>12</UnitStat_Defense_Pierce>
			<UnitStat_HitPoints>6</UnitStat_HitPoints>
			<UnitStat_Intelligence>1</UnitStat_Intelligence>
			<UnitStat_Moves>3</UnitStat_Moves>
			<UnitStat_PathOfTheNecro>1</UnitStat_PathOfTheNecro>
		</LevelMilestone>
		<LevelMilestone InternalName="L19">
			<Level>19</Level>
			<UnitStat_MagicResist>60</UnitStat_MagicResist>
			<UnitStat_MagicPower>97</UnitStat_MagicPower>
			<UnitStat_SpellDamage>60</UnitStat_SpellDamage>
			<UnitStat_Accuracy>75</UnitStat_Accuracy>
			<UnitStat_Attack_Pierce>0</UnitStat_Attack_Pierce>
			<UnitStat_ChanceToCrit>1</UnitStat_ChanceToCrit>
			<UnitStat_CombatSpeed>18</UnitStat_CombatSpeed>
			<UnitStat_Defense_Pierce>12</UnitStat_Defense_Pierce>
			<UnitStat_HitPoints>6</UnitStat_HitPoints>
			<UnitStat_Intelligence>1</UnitStat_Intelligence>
			<UnitStat_Moves>3</UnitStat_Moves>
			<UnitStat_PathOfTheNecro>1</UnitStat_PathOfTheNecro>
		</LevelMilestone>
		<LevelMilestone InternalName="L20">
			<Level>20</Level>
			<UnitStat_MagicResist>60</UnitStat_MagicResist>
			<UnitStat_MagicPower>97</UnitStat_MagicPower>
			<UnitStat_SpellDamage>60</UnitStat_SpellDamage>
			<UnitStat_Accuracy>75</UnitStat_Accuracy>
			<UnitStat_Attack_Pierce>0</UnitStat_Attack_Pierce>
			<UnitStat_ChanceToCrit>1</UnitStat_ChanceToCrit>
			<UnitStat_CombatSpeed>18</UnitStat_CombatSpeed>
			<UnitStat_Defense_Pierce>12</UnitStat_Defense_Pierce>
			<UnitStat_HitPoints>6</UnitStat_HitPoints>
			<UnitStat_Intelligence>1</UnitStat_Intelligence>
			<UnitStat_Moves>3</UnitStat_Moves>
			<UnitStat_PathOfTheNecro>1</UnitStat_PathOfTheNecro>
		</LevelMilestone>
		<SelectedAbilityBonusOption>LichAttributes</SelectedAbilityBonusOption>
		<Equipment>RR_Staff_Furnace</Equipment>
		<Equipment>RR_Ritualist_Robe</Equipment>
		<Medallions InternalName="">
			<All>M_Lich_Card_01.png</All>
		</Medallions>
		<AnimationPack>OldManAnimationPack</AnimationPack>
		<BattleAnimationBehavior>Melee</BattleAnimationBehavior>
		<ClothMapScale>1.5</ClothMapScale>
		<Color_Skin>40,45,50,55</Color_Skin>
		<CutSceneDataPack>DefaultUnitCutscenePack</CutSceneDataPack>
		<EyeTexture>Eyeblink_F4_Blk.png</EyeTexture>
		<InfoCardBackground>BG_Chasm</InfoCardBackground>
		<ModelPath>M_Skeleton_Mesh_01.hkb</ModelPath>
		<ModelScale>1</ModelScale>
		<SkeletonPath>K_Male_Skeleton_01.hkb</SkeletonPath>
		<SoundPack>SoundPack_Skeleton</SoundPack>
		<TacticalModelScale>1.5</TacticalModelScale>
		<Texture_Skin>M_Skeleton_Texture_01.png</Texture_Skin>
		<UnitModelType>RR_Lich</UnitModelType>
		<EffectAttachment>
			<Attachment>Lf_Eye_LCF</Attachment>
			<EffectName>A_LichEyes_Particle</EffectName>
			<EffectPosition>0,0,0</EffectPosition>
			<EffectRotation>0,0,0</EffectRotation>
			<EffectScale>0.1</EffectScale>
		</EffectAttachment>
		<EffectAttachment>
			<Attachment>Rt_Eye_LCF</Attachment>
			<EffectName>A_LichEyes_Particle</EffectName>
			<EffectPosition>0,0,0</EffectPosition>
			<EffectRotation>0,0,0</EffectRotation>
			<EffectScale>0.1</EffectScale>
		</EffectAttachment>
		<AlwaysInTileCenter>1</AlwaysInTileCenter>
		<SelectedAbilityBonusOption>Ability_X_BloodCreatures</SelectedAbilityBonusOption>
	</UnitType>
</UnitTypes>
